<?xml version="1.0" encoding="UTF-8"?>
<files>
  <file name="BVC-0610-to-0645.gif" source="derivative">
    <format>Animated GIF</format>
    <original>BVC-0610-to-0645_jp2.zip</original>
    <mtime>1459409911</mtime>
    <size>297881</size>
    <md5>8eefe195a518c399cc16240aa8f966f0</md5>
    <crc32>4c553dc9</crc32>
    <sha1>6746317d938f75726370a2e4b61ee4e3f06d9bc8</sha1>
  </file>
  <file name="BVC-0610-to-0645.pdf" source="original">
    <mtime>1459409535</mtime>
    <size>28357236</size>
    <md5>860a5b391ef826f258f8faa3040f63db</md5>
    <crc32>64ecf742</crc32>
    <sha1>467302ac12d56b5c47a79ff5a9d57b3304749874</sha1>
    <format>Image Container PDF</format>
  </file>
  <file name="BVC-0610-to-0645_abbyy.gz" source="derivative">
    <format>Abbyy GZ</format>
    <original>BVC-0610-to-0645_jp2.zip</original>
    <mtime>1459411280</mtime>
    <size>755100</size>
    <md5>ff911e974ef7c54d6f1f6470c84aa760</md5>
    <crc32>54e98a05</crc32>
    <sha1>72a46d4f64afe3ec7ab01ca1a647a77ebb0b038d</sha1>
  </file>
  <file name="BVC-0610-to-0645_djvu.txt" source="derivative">
    <format>DjVuTXT</format>
    <original>BVC-0610-to-0645_djvu.xml</original>
    <mtime>1459411302</mtime>
    <size>45359</size>
    <md5>57eb57529532221c4f68d179799f030f</md5>
    <crc32>5f55ea62</crc32>
    <sha1>f18af4451e2658a6e9b550a0549d64bce3fa8da1</sha1>
  </file>
  <file name="BVC-0610-to-0645_djvu.xml" source="derivative">
    <format>Djvu XML</format>
    <original>BVC-0610-to-0645_abbyy.gz</original>
    <mtime>1459411295</mtime>
    <size>514209</size>
    <md5>b95cb85608a03d606c82691f41d2399f</md5>
    <crc32>8842fd56</crc32>
    <sha1>049f0b13f67327f9103d3458dc8758f2d52714f4</sha1>
  </file>
  <file name="BVC-0610-to-0645_jp2.zip" source="derivative">
    <format>Single Page Processed JP2 ZIP</format>
    <original>BVC-0610-to-0645.pdf</original>
    <mtime>1459409880</mtime>
    <size>34037217</size>
    <md5>91fa35a5af46ff01fa8f939835dff1d5</md5>
    <crc32>96391ff7</crc32>
    <sha1>437102dd315b655d136ee521f74a55f608e2bf53</sha1>
  </file>
  <file name="BVC-0610-to-0645_scandata.xml" source="derivative">
    <format>Scandata</format>
    <original>BVC-0610-to-0645_djvu.xml</original>
    <mtime>1459411301</mtime>
    <size>13734</size>
    <md5>5244aff356ba53c2c61da2367f0f583f</md5>
    <crc32>ab5c128e</crc32>
    <sha1>753b58f65fa5fa6e1507791bd8cb2a343329d4d2</sha1>
  </file>
  <file name="BVC-0610-to-0645_text.pdf" source="derivative">
    <format>Additional Text PDF</format>
    <original>BVC-0610-to-0645_djvu.xml</original>
    <mtime>1459411715</mtime>
    <size>8359145</size>
    <md5>bb32db4c52db03e7e6383c3717fe4523</md5>
    <crc32>0aca4ba5</crc32>
    <sha1>fa4cabb1d14f6f282075ece45ba01b78306c48bf</sha1>
  </file>
  <file name="__ia_thumb.jpg" source="original">
    <mtime>1530708890</mtime>
    <size>17921</size>
    <md5>ea8da8bda174af71d30b5fda11a9fbe5</md5>
    <crc32>5e1fcd97</crc32>
    <sha1>a60699d8b84476d25dc96de751ffa154ebef1018</sha1>
    <format>JPEG Thumb</format>
    <rotation>0</rotation>
  </file>
  <file name="collection-of-correspondence-restoration-of-communication-lines-november-1944_archive.torrent" source="metadata">
    <btih>969f32b21f563bd25cd8d6104a2686c53b967f97</btih>
    <mtime>1530708892</mtime>
    <size>6401</size>
    <md5>8e2e7f01362dba591b3acad5b7cbad46</md5>
    <crc32>7c5baf4f</crc32>
    <sha1>65e9c32b540deca48b26ac61d00a8f7f9f3fe920</sha1>
    <format>Archive BitTorrent</format>
  </file>
  <file name="collection-of-correspondence-restoration-of-communication-lines-november-1944_files.xml" source="original">
    <format>Metadata</format>
    <md5>2e43fb83cb690ac3ed2ef7d633dfdc43</md5>
  </file>
  <file name="collection-of-correspondence-restoration-of-communication-lines-november-1944_meta.sqlite" source="original">
    <mtime>1463174406</mtime>
    <size>11264</size>
    <format>Metadata</format>
    <md5>21fbf062dbf549022ba6bc6df5badafe</md5>
    <crc32>838464ea</crc32>
    <sha1>c34ac86c3296f9046cd325b4f9b95767648c107d</sha1>
  </file>
  <file name="collection-of-correspondence-restoration-of-communication-lines-november-1944_meta.xml" source="original">
    <mtime>1484249807</mtime>
    <size>1392</size>
    <format>Metadata</format>
    <md5>8fae1e37843ebe43ff3e3cde1855e8ca</md5>
    <crc32>06732106</crc32>
    <sha1>aa585bd93c1351215ff1665b034de46e3885617c</sha1>
  </file>
</files>
