<?xml version="1.0" encoding="UTF-8"?>
<!DOCTYPE DjVuXML>
<DjVuXML>
<BODY>
<OBJECT data="file://localhost//t/derive/InauguralHymn1971ConstitutionalConvention//Inaugural Hymn 1971 Constitutional Convention.djvu" height="6036" type="image/x.djvu" usemap="Convention_0000.djvu" width="4264">
<PARAM name="PAGE" value="Convention_0000.djvu"/>
<PARAM name="DPI" value="600"/>
<HIDDENTEXT>
<PAGECOLUMN></PAGECOLUMN>
<PAGECOLUMN>
<REGION>
<PARAGRAPH>
<LINE>
<WORD coords="2668,888,2850,782,884">12.</WORD>
<WORD coords="2956,888,3222,776,886">t2E</WORD>
</LINE>
</PARAGRAPH>
</REGION>
</PAGECOLUMN>
<PAGECOLUMN>
<REGION>
<PARAGRAPH>
<LINE>
<WORD coords="1118,1798,1122,1786,1799">,</WORD>
<WORD coords="1256,1796,1486,1664,1794">JOSE</WORD>
<WORD coords="1540,1792,1804,1664,1791">AEAD</WORD>
<WORD coords="1860,1792,2222,1664,1791">SA^rreS</WORD>
<WORD coords="2276,1800,2508,1668,1797">HIGH</WORD>
<WORD coords="2558,1800,2930,1674,1799">SCHOOL</WORD>
</LINE>
</PARAGRAPH>
<PARAGRAPH>
<LINE>
<WORD coords="584,2376,3640,1928,2246">^DAWNOFANEWDAy</WORD>
</LINE>
</PARAGRAPH>
<PARAGRAPH>
<LINE>
<WORD coords="1050,2492,1768,2318,2444">(liwai/waj/</WORD>
<WORD coords="1812,2506,1986,2382,2456">rigf</WORD>
<WORD coords="2022,2510,2510,2352,2452">Bqgfonjr</WORD>
<WORD coords="2544,2512,3118,2334,2455">Pag-asa)</WORD>
</LINE>
</PARAGRAPH>
</REGION>
</PAGECOLUMN>
<PAGECOLUMN>
<REGION>
<PARAGRAPH>
<LINE>
<WORD coords="1576,2976,2126,2832,2938">3na\i£jurai</WORD>
<WORD coords="2234,2974,2604,2842,2940">Hijmn</WORD>
</LINE>
<LINE>
<WORD coords="1160,3102,1380,3008,3103">1971</WORD>
<WORD coords="1438,3116,2166,3010,3110">Constitutional</WORD>
<WORD coords="2222,3122,2864,3016,3114">Convcnixon</WORD>
</LINE>
</PARAGRAPH>
</REGION>
</PAGECOLUMN>
<PAGECOLUMN></PAGECOLUMN>
<PAGECOLUMN>
<REGION>
<PARAGRAPH>
<LINE>
<WORD coords="1290,4298,1854,4134,4294">BHseo</WORD>
<WORD coords="1910,4300,2120,4144,4299">Ni.</WORD>
<WORD coords="2202,4362,2804,4146,4299">Pajaro</WORD>
</LINE>
</PARAGRAPH>
</REGION>
</PAGECOLUMN>
<PAGECOLUMN>
<REGION>
<PARAGRAPH>
<LINE>
<WORD coords="394,4770,824,4630,4767">Horacio</WORD>
<WORD coords="860,4768,990,4632,4768">de</WORD>
<WORD coords="1024,4772,1128,4636,4770">la</WORD>
<WORD coords="1184,4790,1554,4632,4768">Costa,</WORD>
<WORD coords="1584,4776,1794,4642,4775">S.J.</WORD>
</LINE>
</PARAGRAPH>
</REGION>
</PAGECOLUMN>
<PAGECOLUMN>
<REGION>
<PARAGRAPH>
<LINE>
<WORD coords="2532,4808,2962,4634,4770">Rufino</WORD>
<WORD coords="3020,4824,3730,4632,4771">Alejandro</WORD>
</LINE>
</PARAGRAPH>
</REGION>
</PAGECOLUMN>
<PAGECOLUMN>
<REGION>
<PARAGRAPH>
<LINE>
<WORD coords="672,5206,1356,5112,5201">Commiss/oned</WORD>
<WORD coords="1602,5206,1746,5106,5204">/he</WORD>
<WORD coords="1834,5236,2398,5110,5203">Jnau^ural</WORD>
<WORD coords="2464,5202,2998,5106,5197">Co/nmiffee</WORD>
<WORD coords="3096,5202,3230,5112,5201">of</WORD>
<WORD coords="3296,5206,3462,5110,5201">the</WORD>
</LINE>
<LINE>
<WORD coords="1376,5388,2070,5300,5382">CortMllutionat</WORD>
<WORD coords="2138,5382,2752,5284,5376">Convention/</WORD>
</LINE>
</PARAGRAPH>
</REGION>
</PAGECOLUMN>
</HIDDENTEXT>
</OBJECT>
<MAP name="Convention_0000.djvu"/>
<OBJECT data="file://localhost//t/derive/InauguralHymn1971ConstitutionalConvention//Inaugural Hymn 1971 Constitutional Convention.djvu" height="5962" type="image/x.djvu" usemap="Convention_0001.djvu" width="4216">
<PARAM name="PAGE" value="Convention_0001.djvu"/>
<PARAM name="DPI" value="600"/>
<HIDDENTEXT>
<PAGECOLUMN>
<REGION>
<PARAGRAPH>
<LINE>
<WORD coords="1584,446,1924,332,425">&apos;JRifuMit</WORD>
<WORD coords="1992,418,2069,337,417">of</WORD>
<WORD coords="2130,442,2241,337,423">lift</WORD>
<WORD coords="2308,447,2755,331,417">^({tltppuus</WORD>
</LINE>
<LINE>
<WORD coords="1190,577,1406,489,576">1971</WORD>
<WORD coords="1477,578,2379,491,575">CONSTITUTIONAL</WORD>
<WORD coords="2441,583,3152,492,578">CONVENTION</WORD>
</LINE>
</PARAGRAPH>
<PARAGRAPH>
<LINE>
<WORD coords="1841,666,2485,609,663">MANILA</WORD>
</LINE>
</PARAGRAPH>
</REGION>
</PAGECOLUMN>
<PAGECOLUMN>
<REGION>
<PARAGRAPH>
<LINE>
<WORD coords="1448,1084,1870,1029,1082">STATEMENT</WORD>
<WORD coords="1923,1082,2011,1029,1081">ON</WORD>
<WORD coords="2060,1080,2203,1027,1079">THE</WORD>
<WORD coords="2252,1080,2677,1025,1077">INAUGURAL</WORD>
<WORD coords="2726,1081,2913,1027,1080">HYMN</WORD>
</LINE>
</PARAGRAPH>
</REGION>
</PAGECOLUMN>
<PAGECOLUMN>
<REGION>
<PARAGRAPH>
<LINE>
<WORD coords="1401,1400,1439,1347,1400">I</WORD>
<WORD coords="1497,1396,1679,1345,1394">take</WORD>
<WORD coords="1730,1407,1959,1343,1394">pride</WORD>
<WORD coords="2019,1397,2105,1343,1396">in</WORD>
<WORD coords="2159,1408,2581,1345,1397">endorsinf?</WORD>
<WORD coords="2635,1399,2813,1343,1398">this</WORD>
<WORD coords="2867,1406,3295,1345,1402">beautiful</WORD>
</LINE>
<LINE>
<WORD coords="1162,1491,1346,1424,1478">hymn</WORD>
<WORD coords="1396,1476,1724,1420,1473">becauise</WORD>
<WORD coords="1781,1476,1816,1422,1476">I</WORD>
<WORD coords="1874,1473,2053,1420,1472">have</WORD>
<WORD coords="2108,1475,2296,1420,1474">been</WORD>
<WORD coords="2352,1476,2724,1422,1475">Involved</WORD>
<WORD coords="2781,1495,3251,1425,1479">intimtely</WORD>
<WORD coords="3307,1486,3392,1433,1486">in</WORD>
</LINE>
<LINE>
<WORD coords="1164,1560,1293,1503,1559">its</WORD>
<WORD coords="1354,1558,1727,1501,1554">creation</WORD>
<WORD coords="1773,1551,1861,1509,1549">as</WORD>
<WORD coords="1922,1556,2296,1500,1554">Chairman</WORD>
<WORD coords="2348,1556,2435,1504,1556">of</WORD>
<WORD coords="2492,1556,2624,1501,1555">the</WORD>
<WORD coords="2685,1571,3105,1504,1558">Inaugural</WORD>
<WORD coords="3161,1565,3340,1509,1564">Com-</WORD>
</LINE>
<LINE>
<WORD coords="1154,1641,1438,1585,1637">mittee</WORD>
<WORD coords="1494,1635,1582,1578,1634">of</WORD>
<WORD coords="1638,1633,1769,1577,1632">the</WORD>
<WORD coords="1826,1635,2485,1580,1634">Constitutional</WORD>
<WORD coords="2541,1640,3012,1582,1637">Convention</WORD>
<WORD coords="3061,1645,3299,1588,1643">which</WORD>
</LINE>
<LINE>
<WORD coords="1160,1718,1724,1659,1715">commissioned</WORD>
<WORD coords="1781,1713,1863,1659,1713">it</WORD>
<WORD coords="1912,1713,2000,1670,1712">as</WORD>
<WORD coords="2060,1715,2198,1673,1714">our</WORD>
<WORD coords="2256,1729,2676,1661,1715">inaugural</WORD>
<WORD coords="2728,1730,2945,1662,1721">hsnnn.</WORD>
</LINE>
</PARAGRAPH>
</REGION>
</PAGECOLUMN>
<PAGECOLUMN>
<REGION>
<PARAGRAPH>
<LINE>
<WORD coords="1399,1955,1483,1899,1953">It</WORD>
<WORD coords="1542,1950,1623,1897,1949">is</WORD>
<WORD coords="1677,1961,1773,1909,1949">my</WORD>
<WORD coords="1825,1964,2003,1896,1950">hope</WORD>
<WORD coords="2061,1952,2245,1897,1950">that</WORD>
<WORD coords="2302,1966,2534,1911,1953">every</WORD>
<WORD coords="2589,1960,2914,1903,1957">citizen</WORD>
<WORD coords="2969,1963,3057,1910,1962">of</WORD>
<WORD coords="3113,1966,3291,1909,1964">this</WORD>
</LINE>
<LINE>
<WORD coords="1158,2042,1520,1977,2030">country,</WORD>
<WORD coords="1585,2043,2154,1975,2027">particularly</WORD>
<WORD coords="2206,2031,2342,1990,2031">our</WORD>
<WORD coords="2397,2035,2676,1979,2032">school</WORD>
<WORD coords="2732,2055,3138,1983,2038">children,</WORD>
<WORD coords="3203,2048,3389,1993,2045">will</WORD>
</LINE>
<LINE>
<WORD coords="1158,2108,1394,2056,2106">learn</WORD>
<WORD coords="1444,2106,1533,2054,2105">to</WORD>
<WORD coords="1588,2118,1773,2054,2104">sing</WORD>
<WORD coords="1827,2107,1911,2054,2106">it</WORD>
<WORD coords="1963,2118,2057,2053,2105">by</WORD>
<WORD coords="2111,2108,2340,2054,2106">heart</WORD>
<WORD coords="2392,2108,2482,2067,2107">as</WORD>
<WORD coords="2535,2107,2577,2069,2107">a</WORD>
<WORD coords="2637,2126,2820,2072,2112">song</WORD>
<WORD coords="2873,2116,2961,2064,2116">of</WORD>
<WORD coords="3015,2131,3339,2067,2119">patrio-</WORD>
</LINE>
<LINE>
<WORD coords="1157,2184,1376,2132,2183">tism.</WORD>
</LINE>
</PARAGRAPH>
</REGION>
</PAGECOLUMN>
<PAGECOLUMN>
<REGION>
<PARAGRAPH>
<LINE>
<WORD coords="2644,2360,2663,2331,2360">ft</WORD>
</LINE>
</PARAGRAPH>
<PARAGRAPH>
<LINE>
<WORD coords="2495,2585,2772,2525,2582">CICERO</WORD>
<WORD coords="2824,2592,2898,2534,2589">D.</WORD>
<WORD coords="2969,2598,3345,2535,2594">GALDERON</WORD>
<WORD coords="3588,2589,3608,2530,2589">I</WORD>
</LINE>
</PARAGRAPH>
<PARAGRAPH>
<LINE>
<WORD coords="2731,2673,3108,2611,2668">Chairman</WORD>
</LINE>
<LINE>
<WORD coords="2498,2758,2913,2689,2745">Inaugural</WORD>
<WORD coords="2970,2758,3388,2700,2756">Committee</WORD>
</LINE>
</PARAGRAPH>
</REGION>
</PAGECOLUMN>
<PAGECOLUMN></PAGECOLUMN>
<PAGECOLUMN>
<REGION>
<PARAGRAPH>
<LINE>
<WORD coords="1872,3399,2290,3353,3398">REPUBUKA</WORD>
<WORD coords="2316,3402,2422,3356,3401">NG</WORD>
<WORD coords="2451,3410,2802,3357,3405">PIUPINAS</WORD>
</LINE>
</PARAGRAPH>
<PARAGRAPH>
<LINE>
<WORD coords="1975,3457,2194,3422,3456">RfiKitUC</WORD>
<WORD coords="2215,3458,2282,3424,3457">OF</WORD>
<WORD coords="2300,3460,2390,3423,3459">THE</WORD>
<WORD coords="2413,3466,2691,3426,3462">MIUPPINES</WORD>
</LINE>
</PARAGRAPH>
<PARAGRAPH>
<LINE>
<WORD coords="1605,3548,2252,3486,3545">KAGAWARAN</WORD>
<WORD coords="2286,3547,2422,3489,3546">NG</WORD>
<WORD coords="2455,3560,3056,3491,3554">EDUKASYON</WORD>
</LINE>
</PARAGRAPH>
<PARAGRAPH>
<LINE>
<WORD coords="1989,3605,2294,3568,3604">DEPAKTMGNT</WORD>
<WORD coords="2314,3605,2380,3570,3605">OF</WORD>
<WORD coords="2401,3611,2672,3572,3609">EDUCATION</WORD>
</LINE>
<LINE>
<WORD coords="2162,3683,2505,3636,3681">MAYNILA</WORD>
</LINE>
<LINE>
<WORD coords="2248,3744,2430,3705,3742">MANILA</WORD>
</LINE>
</PARAGRAPH>
</REGION>
</PAGECOLUMN>
<PAGECOLUMN>
<REGION>
<PARAGRAPH>
<LINE>
<WORD coords="684,3949,1150,3902,3948">TANOCAPAN</WORD>
<WORD coords="1179,3949,1284,3903,3948">NG</WORD>
<WORD coords="1315,3947,1639,3901,3946">KAUHIM</WORD>
</LINE>
</PARAGRAPH>
<PARAGRAPH>
<LINE>
<WORD coords="838,4010,1001,3971,4008">OFFICI</WORD>
<WORD coords="1022,4010,1089,3973,4009">OF</WORD>
<WORD coords="1106,4010,1197,3972,4009">THS</WORD>
<WORD coords="1220,4010,1478,3973,4009">SECRETARY</WORD>
</LINE>
</PARAGRAPH>
</REGION>
</PAGECOLUMN>
<PAGECOLUMN>
<REGION>
<PARAGRAPH>
<LINE>
<WORD coords="1322,4626,1460,4567,4625">The</WORD>
<WORD coords="1518,4637,1716,4566,4622">hymn</WORD>
<WORD coords="1775,4626,1953,4563,4624">&quot;The</WORD>
<WORD coords="2014,4625,2202,4564,4624">Dawn</WORD>
<WORD coords="2258,4627,2345,4565,4626">of</WORD>
<WORD coords="2400,4626,2442,4582,4626">a</WORD>
<WORD coords="2503,4634,2639,4572,4631">New</WORD>
<WORD coords="2695,4651,2878,4575,4634">Day&quot;</WORD>
<WORD coords="2945,4640,3030,4579,4639">ia</WORD>
<WORD coords="3086,4637,3130,4593,4637">a</WORD>
</LINE>
<LINE>
<WORD coords="1034,4717,1462,4655,4714">beautiful</WORD>
<WORD coords="1522,4704,2054,4645,4703">combination</WORD>
<WORD coords="2113,4705,2196,4648,4704">of</WORD>
<WORD coords="2259,4725,2587,4649,4707">thought</WORD>
<WORD coords="2643,4718,2788,4659,4714">and</WORD>
<WORD coords="2845,4737,3180,4659,4719">feeling</WORD>
</LINE>
<LINE>
<WORD coords="1030,4819,1512,4741,4801">eloquently</WORD>
<WORD coords="1572,4818,2049,4745,4802">expressing</WORD>
<WORD coords="2111,4806,2242,4749,4804">the</WORD>
<WORD coords="2297,4818,2536,4748,4805">hopes</WORD>
<WORD coords="2591,4815,2736,4757,4811">and</WORD>
<WORD coords="2787,4829,3324,4758,4816">aspirations</WORD>
</LINE>
<LINE>
<WORD coords="1031,4890,1117,4830,4889">of</WORD>
<WORD coords="1178,4892,1314,4849,4891">our</WORD>
<WORD coords="1370,4908,1694,4835,4894">people.</WORD>
<WORD coords="1818,4898,1949,4835,4895">Its</WORD>
<WORD coords="2010,4900,2340,4840,4896">cadence</WORD>
<WORD coords="2405,4899,2489,4838,4898">is</WORD>
<WORD coords="2544,4917,2928,4846,4903">majestic</WORD>
<WORD coords="2986,4906,3135,4849,4904">and</WORD>
<WORD coords="3183,4906,3377,4860,4903">awe-</WORD>
</LINE>
<LINE>
<WORD coords="1029,4988,1493,4909,4970">inspiring.</WORD>
<WORD coords="1614,4975,1754,4915,4974">Our</WORD>
<WORD coords="1809,4979,2195,4918,4976">children</WORD>
<WORD coords="2246,4981,2391,4922,4978">and</WORD>
<WORD coords="2443,4993,2729,4925,4982">youths</WORD>
<WORD coords="2791,4986,3081,4926,4984">should</WORD>
<WORD coords="3137,4988,3424,4927,4985">under-</WORD>
</LINE>
<LINE>
<WORD coords="1028,5060,1266,4996,5054">stand</WORD>
<WORD coords="1315,5061,1461,5003,5058">and</WORD>
<WORD coords="1518,5075,1705,5002,5060">sing</WORD>
<WORD coords="1764,5061,1895,5004,5060">the</WORD>
<WORD coords="1952,5075,2147,5006,5063">hymn</WORD>
<WORD coords="2205,5077,2291,5008,5063">by</WORD>
<WORD coords="2343,5069,2581,5010,5067">heart</WORD>
<WORD coords="2636,5073,2831,5013,5070">with</WORD>
<WORD coords="2888,5071,3029,5027,5071">our</WORD>
<WORD coords="3083,5075,3469,5011,5070">national</WORD>
</LINE>
<LINE>
<WORD coords="1022,5148,1314,5086,5143">anthem</WORD>
<WORD coords="1369,5164,1657,5089,5148">during</WORD>
<WORD coords="1718,5149,1849,5090,5148">the</WORD>
<WORD coords="1912,5163,2100,5089,5146">flag</WORD>
<WORD coords="2155,5163,2543,5106,5149">ceremony</WORD>
<WORD coords="2599,5152,2688,5095,5151">in</WORD>
<WORD coords="2745,5157,2884,5113,5155">our</WORD>
<WORD coords="2942,5158,3314,5095,5155">schools.</WORD>
</LINE>
</PARAGRAPH>
</REGION>
</PAGECOLUMN>
<PAGECOLUMN>
<REGION>
<PARAGRAPH>
<LINE>
<WORD coords="2051,5563,2487,5466,5547">/^AN^L.</WORD>
<WORD coords="2558,5552,2844,5487,5549">MANUAL</WORD>
</LINE>
<LINE>
<WORD coords="2109,5630,2405,5559,5615">Acting</WORD>
<WORD coords="2462,5634,2895,5559,5617">Secretary</WORD>
</LINE>
</PARAGRAPH>
</REGION>
</PAGECOLUMN>
</HIDDENTEXT>
</OBJECT>
<MAP name="Convention_0001.djvu"/>
<OBJECT data="file://localhost//t/derive/InauguralHymn1971ConstitutionalConvention//Inaugural Hymn 1971 Constitutional Convention.djvu" height="6018" type="image/x.djvu" usemap="Convention_0002.djvu" width="4278">
<PARAM name="PAGE" value="Convention_0002.djvu"/>
<PARAM name="DPI" value="600"/>
<HIDDENTEXT>
<PAGECOLUMN>
<REGION>
<PARAGRAPH>
<LINE>
<WORD coords="1124,349,1476,302,346">CommisBioncd</WORD>
<WORD coords="1504,356,1563,302,344">by</WORD>
<WORD coords="1593,344,1665,302,343">the</WORD>
<WORD coords="1698,357,1926,301,342">Inaugural</WORD>
<WORD coords="1956,343,2219,301,341">Committee</WORD>
<WORD coords="2246,342,2296,300,341">of</WORD>
<WORD coords="2319,342,2394,300,341">tlie</WORD>
<WORD coords="2423,345,2761,301,343">Constitutional</WORD>
<WORD coords="2793,344,3070,302,343">Convention</WORD>
</LINE>
</PARAGRAPH>
<PARAGRAPH>
<LINE>
<WORD coords="852,512,1232,388,512">THE</WORD>
<WORD coords="1296,508,1884,388,508">DAWN</WORD>
<WORD coords="1952,512,2188,384,510">OF</WORD>
<WORD coords="2252,504,2372,384,504">A</WORD>
<WORD coords="2436,508,2876,388,508">NEW</WORD>
<WORD coords="2944,512,3332,388,510">DAY</WORD>
</LINE>
</PARAGRAPH>
</REGION>
</PAGECOLUMN>
<PAGECOLUMN>
<REGION>
<PARAGRAPH>
<LINE>
<WORD coords="248,688,592,540,685">&apos;&apos;Ho^cio</WORD>
<WORD coords="624,684,708,616,684">d=</WORD>
<WORD coords="740,680,800,616,680">la</WORD>
<WORD coords="828,692,1048,616,680">Costa,</WORD>
<WORD coords="1080,692,1208,612,686">S.J.</WORD>
<WORD coords="1284,660,1816,548,632">(Liwayway</WORD>
<WORD coords="1880,660,1996,580,632">ng</WORD>
<WORD coords="2064,660,2416,552,632">Bagong</WORD>
<WORD coords="2480,660,2900,552,634">Pag-asa)</WORD>
</LINE>
</PARAGRAPH>
</REGION>
</PAGECOLUMN>
<PAGECOLUMN>
<REGION>
<PARAGRAPH>
<LINE>
<WORD coords="252,799,468,735,784">Filipino</WORD>
<WORD coords="502,781,820,730,778">Translation</WORD>
<WORD coords="853,792,911,727,777">by</WORD>
</LINE>
<LINE>
<WORD coords="310,884,449,820,882">Ruf</WORD>
<WORD coords="458,880,566,820,879">ino</WORD>
<WORD coords="597,896,950,814,876">Alejandro</WORD>
</LINE>
</PARAGRAPH>
<PARAGRAPH>
<LINE>
<WORD coords="843,964,1169,896,960">Maestoso</WORD>
</LINE>
</PARAGRAPH>
<PARAGRAPH>
<LINE>
<WORD coords="285,1162,475,1113,1160">ALTO</WORD>
</LINE>
</PARAGRAPH>
</REGION>
</PAGECOLUMN>
<PAGECOLUMN>
<REGION>
<PARAGRAPH>
<LINE>
<WORD coords="1815,776,2164,696,756">Inaugural</WORD>
<WORD coords="2204,774,2431,695,755">Hymn</WORD>
</LINE>
<LINE>
<WORD coords="1617,843,2116,778,842">Constitutional</WORD>
<WORD coords="2159,844,2573,777,841">Convention</WORD>
</LINE>
</PARAGRAPH>
</REGION>
</PAGECOLUMN>
<PAGECOLUMN>
<REGION>
<PARAGRAPH>
<LINE>
<WORD coords="3251,789,3416,739,787">Music</WORD>
<WORD coords="3444,804,3503,740,789">by</WORD>
</LINE>
</PARAGRAPH>
<PARAGRAPH>
<LINE>
<WORD coords="3307,881,3525,816,879">Eliseo</WORD>
<WORD coords="3559,882,3658,818,882">M.</WORD>
<WORD coords="3703,903,3938,819,884">Pajaro</WORD>
</LINE>
</PARAGRAPH>
</REGION>
</PAGECOLUMN>
<PAGECOLUMN></PAGECOLUMN>
<PAGECOLUMN>
<REGION>
<PARAGRAPH>
<LINE>
<WORD coords="282,5729,538,5670,5715">Copyright,</WORD>
<WORD coords="572,5725,691,5674,5719">1971,</WORD>
<WORD coords="723,5727,780,5674,5715">by</WORD>
<WORD coords="810,5723,950,5673,5719">Eliseo</WORD>
<WORD coords="980,5727,1047,5684,5726">M.</WORD>
<WORD coords="1078,5741,1224,5686,5728">Pajaro</WORD>
</LINE>
</PARAGRAPH>
</REGION>
</PAGECOLUMN>
<PAGECOLUMN>
<REGION>
<PARAGRAPH>
<LINE>
<WORD coords="1827,5708,1854,5681,5716">*</WORD>
<WORD coords="1878,5725,1966,5681,5724">The</WORD>
<WORD coords="1992,5739,2117,5683,5727">lyrics</WORD>
<WORD coords="2146,5729,2231,5699,5727">was</WORD>
<WORD coords="2258,5737,2466,5683,5723">approved</WORD>
<WORD coords="2491,5737,2543,5681,5724">by</WORD>
<WORD coords="2571,5724,2626,5695,5723">an</WORD>
<WORD coords="2654,5723,2910,5672,5717">Ecumenical</WORD>
<WORD coords="2936,5716,3178,5673,5713">Committee</WORD>
<WORD coords="3209,5719,3335,5677,5717">wider</WORD>
<WORD coords="3364,5740,3521,5681,5723">Bishop</WORD>
<WORD coords="3549,5731,3752,5688,5730">Mariano</WORD>
<WORD coords="3784,5743,3967,5693,5739">Gaviola</WORD>
</LINE>
</PARAGRAPH>
</REGION>
</PAGECOLUMN>
</HIDDENTEXT>
</OBJECT>
<MAP name="Convention_0002.djvu"/>
<OBJECT data="file://localhost//t/derive/InauguralHymn1971ConstitutionalConvention//Inaugural Hymn 1971 Constitutional Convention.djvu" height="6028" type="image/x.djvu" usemap="Convention_0003.djvu" width="4184">
<PARAM name="PAGE" value="Convention_0003.djvu"/>
<PARAM name="DPI" value="600"/>
<HIDDENTEXT>
<PAGECOLUMN>
<REGION>
<PARAGRAPH>
<LINE>
<WORD coords="2084,496,2192,430,496">•z-</WORD>
</LINE>
</PARAGRAPH>
</REGION>
</PAGECOLUMN>
<PAGECOLUMN>
<REGION>
<PARAGRAPH>
<LINE>
<WORD coords="607,921,826,822,893">fou^kt</WORD>
<WORD coords="884,894,1007,827,892">ani</WORD>
<WORD coords="1130,898,1283,827,895">died</WORD>
</LINE>
<LINE>
<WORD coords="908,999,976,938,996">la</WORD>
<WORD coords="1034,989,1065,978,995">^</WORD>
<WORD coords="1157,1018,1262,939,1002">hi;</WORD>
</LINE>
</PARAGRAPH>
</REGION>
</PAGECOLUMN>
<PAGECOLUMN></PAGECOLUMN>
<PAGECOLUMN>
<REGION>
<PARAGRAPH>
<LINE>
<WORD coords="1660,896,1870,812,892">7cack</WORD>
<WORD coords="1944,900,2023,854,898">as</WORD>
<WORD coords="2183,898,2333,818,895">feU</WORD>
<WORD coords="2375,896,2497,827,895">low</WORD>
<WORD coords="2513,924,2677,835,898">-skip</WORD>
<WORD coords="2822,907,2952,845,905">Owe</WORD>
<WORD coords="3177,914,3317,851,911">wlik</WORD>
<WORD coords="3373,918,3627,855,916">a-nolk</WORD>
<WORD coords="3667,902,3699,892,903">-</WORD>
<WORD coords="3781,919,3888,877,917">ar.</WORD>
</LINE>
</PARAGRAPH>
</REGION>
</PAGECOLUMN>
<PAGECOLUMN></PAGECOLUMN>
<PAGECOLUMN>
<REGION>
<PARAGRAPH>
<LINE>
<WORD coords="564,2564,770,2498,2562">Based</WORD>
<WORD coords="881,2564,962,2527,2563">on</WORD>
</LINE>
</PARAGRAPH>
</REGION>
</PAGECOLUMN>
<PAGECOLUMN>
<REGION>
<PARAGRAPH>
<LINE>
<WORD coords="534,2696,711,2611,2685">yJInQ</WORD>
<WORD coords="852,2689,947,2623,2688">ha,</WORD>
<WORD coords="1011,2676,1039,2666,2676">&quot;</WORD>
</LINE>
</PARAGRAPH>
</REGION>
</PAGECOLUMN>
<PAGECOLUMN>
<REGION>
<PARAGRAPH>
<LINE>
<WORD coords="1694,2577,1869,2498,2575">Built</WORD>
<WORD coords="2002,2579,2081,2540,2579">on</WORD>
<WORD coords="2179,2593,2325,2509,2588">Jus</WORD>
<WORD coords="2357,2590,2440,2535,2590">-I</WORD>
<WORD coords="2452,2596,2541,2554,2593">ICC</WORD>
</LINE>
</PARAGRAPH>
</REGION>
</PAGECOLUMN>
<PAGECOLUMN>
<REGION>
<PARAGRAPH>
<LINE>
<WORD coords="2879,2619,3060,2542,2615">Born</WORD>
<WORD coords="3135,2624,3212,2547,2623">of</WORD>
<WORD coords="3343,2646,3536,2551,2629">iLovQ,</WORD>
<WORD coords="3603,2639,3928,2560,2633">flow-cr-</WORD>
</LINE>
<LINE>
<WORD coords="3112,2775,3316,2704,2745">paj^</WORD>
<WORD coords="3401,2756,3435,2687,2756">i</WORD>
<WORD coords="3484,2743,3512,2732,2744">,</WORD>
<WORD coords="3605,2786,3740,2697,2772">^^^^</WORD>
</LINE>
</PARAGRAPH>
</REGION>
</PAGECOLUMN>
</HIDDENTEXT>
</OBJECT>
<MAP name="Convention_0003.djvu"/>
<OBJECT data="file://localhost//t/derive/InauguralHymn1971ConstitutionalConvention//Inaugural Hymn 1971 Constitutional Convention.djvu" height="6035" type="image/x.djvu" usemap="Convention_0004.djvu" width="4264">
<PARAM name="PAGE" value="Convention_0004.djvu"/>
<PARAM name="DPI" value="600"/>
<HIDDENTEXT>
<PAGECOLUMN>
<REGION>
<PARAGRAPH>
<LINE>
<WORD coords="2948,934,3104,871,931">God</WORD>
<WORD coords="3243,935,3389,899,934">com</WORD>
<WORD coords="3408,921,3425,912,929">-</WORD>
<WORD coords="3445,956,3884,876,934">pas-sio-»iat^</WORD>
</LINE>
<LINE>
<WORD coords="2969,1055,3021,992,1057">0</WORD>
<WORD coords="3251,1056,3373,992,1055">Po&apos;</WORD>
<WORD coords="3389,1088,3512,1021,1057">on^</WORD>
<WORD coords="3529,1084,3741,990,1058">Diijos</WORD>
</LINE>
</PARAGRAPH>
</REGION>
</PAGECOLUMN>
<PAGECOLUMN>
<REGION>
<PARAGRAPH>
<LINE>
<WORD coords="602,940,758,868,937">God.</WORD>
</LINE>
<LINE>
<WORD coords="640,1060,692,1000,1060">0</WORD>
</LINE>
</PARAGRAPH>
</REGION>
</PAGECOLUMN>
<PAGECOLUMN>
<REGION>
<PARAGRAPH>
<LINE>
<WORD coords="939,938,1015,899,936">CO</WORD>
<WORD coords="1023,933,1084,900,933">m</WORD>
<WORD coords="1100,920,1118,912,923">-</WORD>
<WORD coords="1127,952,1236,895,934">pas</WORD>
<WORD coords="1248,919,1268,910,923">-</WORD>
<WORD coords="1277,934,1309,896,934">s</WORD>
<WORD coords="1319,931,1377,896,931">lo</WORD>
<WORD coords="1394,919,1409,910,923">-</WORD>
<WORD coords="1420,927,1458,893,927">H</WORD>
<WORD coords="1467,929,1570,869,927">aie</WORD>
</LINE>
</PARAGRAPH>
</REGION>
</PAGECOLUMN>
<PAGECOLUMN>
<REGION>
<PARAGRAPH>
<LINE>
<WORD coords="984,1348,1404,1104,1348">m</WORD>
</LINE>
</PARAGRAPH>
</REGION>
</PAGECOLUMN>
<PAGECOLUMN>
<REGION>
<PARAGRAPH>
<LINE>
<WORD coords="1787,926,1935,863,925">and</WORD>
<WORD coords="2045,929,2179,890,926">mcr</WORD>
<WORD coords="2213,914,2236,906,919">-</WORD>
<WORD coords="2275,923,2337,859,923">cl</WORD>
<WORD coords="2358,944,2536,864,929">-ful,</WORD>
</LINE>
</PARAGRAPH>
</REGION>
</PAGECOLUMN>
<PAGECOLUMN>
<REGION>
<PARAGRAPH>
<LINE>
<WORD coords="3692,1336,3800,1192,1336">i</WORD>
</LINE>
</PARAGRAPH>
</REGION>
</PAGECOLUMN>
<PAGECOLUMN>
<REGION>
<PARAGRAPH>
<LINE>
<WORD coords="1128,1872,1220,1780,1872">*</WORD>
<WORD coords="1268,1864,1360,1780,1868">*</WORD>
<WORD coords="1412,1864,1508,1776,1864">*</WORD>
</LINE>
</PARAGRAPH>
</REGION>
</PAGECOLUMN>
<PAGECOLUMN>
<REGION>
<PARAGRAPH>
<LINE>
<WORD coords="3596,1774,3772,1726,1773">1=3</WORD>
</LINE>
</PARAGRAPH>
</REGION>
</PAGECOLUMN>
<PAGECOLUMN>
<REGION>
<PARAGRAPH>
<LINE>
<WORD coords="1864,2120,1876,1988,2120">I</WORD>
<WORD coords="2128,2068,2140,1972,2068">I</WORD>
<WORD coords="2424,2124,2436,2076,2124">.</WORD>
<WORD coords="2456,2128,2812,1952,2126">nri</WORD>
</LINE>
</PARAGRAPH>
</REGION>
</PAGECOLUMN>
<PAGECOLUMN>
<REGION>
<PARAGRAPH>
<LINE>
<WORD coords="3296,1876,3808,1776,1874">****</WORD>
</LINE>
</PARAGRAPH>
<PARAGRAPH>
<LINE>
<WORD coords="3224,2112,3280,1988,2112">J</WORD>
<WORD coords="3472,2112,3516,1980,2112">J</WORD>
<WORD coords="3752,2112,3936,1968,2112">n</WORD>
</LINE>
</PARAGRAPH>
</REGION>
</PAGECOLUMN>
<PAGECOLUMN>
<REGION>
<PARAGRAPH></PARAGRAPH>
</REGION>
<REGION>
<PARAGRAPH></PARAGRAPH>
</REGION>
<REGION>
<PARAGRAPH></PARAGRAPH>
</REGION>
<REGION>
<PARAGRAPH></PARAGRAPH>
</REGION>
<REGION>
<PARAGRAPH></PARAGRAPH>
</REGION>
<REGION>
<PARAGRAPH></PARAGRAPH>
</REGION>
<REGION>
<PARAGRAPH></PARAGRAPH>
</REGION>
<REGION>
<PARAGRAPH></PARAGRAPH>
</REGION>
<REGION>
<PARAGRAPH></PARAGRAPH>
</REGION>
<REGION>
<PARAGRAPH></PARAGRAPH>
</REGION>
<REGION>
<PARAGRAPH></PARAGRAPH>
</REGION>
<REGION>
<PARAGRAPH></PARAGRAPH>
</REGION>
<REGION>
<PARAGRAPH></PARAGRAPH>
</REGION>
<REGION>
<PARAGRAPH></PARAGRAPH>
</REGION>
<REGION>
<PARAGRAPH></PARAGRAPH>
</REGION>
<REGION>
<PARAGRAPH></PARAGRAPH>
</REGION>
<REGION>
<PARAGRAPH>
<LINE>
<WORD coords="666,2592,668,2494,2560">1</WORD>
<WORD coords="668,2528,896,2516,2620">—</WORD>
<WORD coords="898,2620,948,2494,0">p</WORD>
</LINE>
</PARAGRAPH>
</REGION>
<REGION>
<PARAGRAPH>
<LINE>
<WORD coords="1056,2632,1226,2494,2600">pi</WORD>
<WORD coords="1768,2632,1862,2494,2632">t</WORD>
<WORD coords="2044,2632,2176,2516,2632">T</WORD>
<WORD coords="2248,2632,2312,2494,2632">i</WORD>
</LINE>
</PARAGRAPH>
</REGION>
<REGION>
<PARAGRAPH></PARAGRAPH>
</REGION>
<REGION>
<PARAGRAPH></PARAGRAPH>
</REGION>
<REGION>
<PARAGRAPH></PARAGRAPH>
</REGION>
<REGION>
<PARAGRAPH></PARAGRAPH>
</REGION>
<REGION>
<PARAGRAPH></PARAGRAPH>
</REGION>
<REGION>
<PARAGRAPH></PARAGRAPH>
</REGION>
</PAGECOLUMN>
<PAGECOLUMN>
<REGION>
<PARAGRAPH>
<LINE>
<WORD coords="672,2826,722,2792,2826">a</WORD>
<WORD coords="758,2818,790,2808,2821">-</WORD>
<WORD coords="850,2830,1036,2764,2826">wa&apos;i</WORD>
<WORD coords="1066,2844,1354,2756,2819">ha-ba^,</WORD>
</LINE>
</PARAGRAPH>
</REGION>
</PAGECOLUMN>
<PAGECOLUMN>
<REGION>
<PARAGRAPH>
<LINE>
<WORD coords="2040,2840,2222,2774,2806">min^</WORD>
<WORD coords="2274,2815,2564,2744,2810">da-sal:</WORD>
<WORD coords="2689,2821,2898,2742,2817">^SiL-</WORD>
</LINE>
</PARAGRAPH>
</REGION>
</PAGECOLUMN>
<PAGECOLUMN></PAGECOLUMN>
<PAGECOLUMN></PAGECOLUMN>
<PAGECOLUMN>
<REGION>
<PARAGRAPH>
<LINE>
<WORD coords="346,4104,374,4067,4104">J</WORD>
</LINE>
</PARAGRAPH>
</REGION>
<REGION>
<PARAGRAPH></PARAGRAPH>
</REGION>
<REGION>
<PARAGRAPH></PARAGRAPH>
</REGION>
<REGION>
<PARAGRAPH></PARAGRAPH>
</REGION>
<REGION>
<PARAGRAPH></PARAGRAPH>
</REGION>
<REGION>
<PARAGRAPH>
<LINE>
<WORD coords="3034,4041,3248,4003,4040">cresc.</WORD>
<WORD coords="3279,4037,3301,4027,4038">-</WORD>
<WORD coords="3355,4036,3373,4028,4036">-</WORD>
</LINE>
</PARAGRAPH>
</REGION>
<REGION>
<PARAGRAPH></PARAGRAPH>
</REGION>
<REGION>
<PARAGRAPH></PARAGRAPH>
</REGION>
<REGION>
<PARAGRAPH></PARAGRAPH>
</REGION>
<REGION>
<PARAGRAPH></PARAGRAPH>
</REGION>
<REGION>
<PARAGRAPH></PARAGRAPH>
</REGION>
<REGION>
<PARAGRAPH></PARAGRAPH>
</REGION>
<REGION>
<PARAGRAPH></PARAGRAPH>
</REGION>
<REGION>
<PARAGRAPH></PARAGRAPH>
</REGION>
<REGION>
<PARAGRAPH></PARAGRAPH>
</REGION>
<REGION>
<PARAGRAPH></PARAGRAPH>
</REGION>
<REGION>
<PARAGRAPH></PARAGRAPH>
</REGION>
<REGION>
<PARAGRAPH></PARAGRAPH>
</REGION>
<REGION>
<PARAGRAPH></PARAGRAPH>
</REGION>
<REGION>
<PARAGRAPH></PARAGRAPH>
</REGION>
<REGION>
<PARAGRAPH></PARAGRAPH>
</REGION>
<REGION>
<PARAGRAPH></PARAGRAPH>
</REGION>
<REGION>
<PARAGRAPH></PARAGRAPH>
</REGION>
<REGION>
<PARAGRAPH></PARAGRAPH>
</REGION>
<REGION>
<PARAGRAPH></PARAGRAPH>
</REGION>
<REGION>
<PARAGRAPH></PARAGRAPH>
</REGION>
<REGION>
<PARAGRAPH></PARAGRAPH>
</REGION>
<REGION>
<PARAGRAPH></PARAGRAPH>
</REGION>
<REGION>
<PARAGRAPH></PARAGRAPH>
</REGION>
<REGION>
<PARAGRAPH></PARAGRAPH>
</REGION>
<REGION>
<PARAGRAPH></PARAGRAPH>
</REGION>
<REGION>
<PARAGRAPH></PARAGRAPH>
</REGION>
<REGION>
<PARAGRAPH></PARAGRAPH>
</REGION>
</PAGECOLUMN>
<PAGECOLUMN>
<REGION>
<PARAGRAPH>
<LINE>
<WORD coords="563,4422,766,4363,4419">down</WORD>
<WORD coords="1191,4411,1269,4352,4411">of</WORD>
<WORD coords="1385,4401,1436,4363,4401">a</WORD>
<WORD coords="1548,4401,1697,4360,4398">new</WORD>
<WORD coords="1846,4424,1986,4352,4393">aaij</WORD>
</LINE>
</PARAGRAPH>
</REGION>
</PAGECOLUMN>
<PAGECOLUMN>
<REGION>
<PARAGRAPH>
<LINE>
<WORD coords="2799,4406,2961,4340,4402">Give</WORD>
<WORD coords="3122,4402,3204,4365,4401">us</WORD>
<WORD coords="3306,4407,3403,4348,4404">tke</WORD>
<WORD coords="3467,4439,3645,4349,4408">li^Ul</WORD>
<WORD coords="3882,4423,3963,4356,4421">to</WORD>
</LINE>
<LINE>
<WORD coords="2926,4509,2959,4498,4519">-</WORD>
<WORD coords="3086,4560,3293,4489,4525">HtiH.^</WORD>
<WORD coords="3318,4535,3614,4472,4530">da-sul:</WORD>
</LINE>
</PARAGRAPH>
</REGION>
</PAGECOLUMN>
</HIDDENTEXT>
</OBJECT>
<MAP name="Convention_0004.djvu"/>
<OBJECT data="file://localhost//t/derive/InauguralHymn1971ConstitutionalConvention//Inaugural Hymn 1971 Constitutional Convention.djvu" height="6028" type="image/x.djvu" usemap="Convention_0005.djvu" width="4212">
<PARAM name="PAGE" value="Convention_0005.djvu"/>
<PARAM name="DPI" value="600"/>
<HIDDENTEXT>
<PAGECOLUMN>
<REGION>
<PARAGRAPH>
<LINE>
<WORD coords="2068,540,2158,472,530">4-</WORD>
</LINE>
</PARAGRAPH>
</REGION>
</PAGECOLUMN>
<PAGECOLUMN></PAGECOLUMN>
<PAGECOLUMN>
<REGION>
<PARAGRAPH>
<LINE>
<WORD coords="568,928,690,860,927">Uv«</WORD>
<WORD coords="818,920,946,856,918">omA</WORD>
</LINE>
</PARAGRAPH>
</REGION>
</PAGECOLUMN>
<PAGECOLUMN>
<REGION>
<PARAGRAPH>
<LINE>
<WORD coords="1772,918,1983,853,915">dawn,</WORD>
</LINE>
<LINE>
<WORD coords="1760,1039,1873,968,1039">3a</WORD>
<WORD coords="1945,1020,1977,1009,1020">-</WORD>
</LINE>
</PARAGRAPH>
</REGION>
</PAGECOLUMN>
<PAGECOLUMN>
<REGION>
<PARAGRAPH>
<LINE>
<WORD coords="2315,914,2396,840,914">of</WORD>
<WORD coords="2473,912,2525,874,912">a</WORD>
<WORD coords="2630,909,2781,869,907">HGw</WORD>
<WORD coords="2985,942,3155,846,908">d^y-</WORD>
</LINE>
</PARAGRAPH>
</REGION>
</PAGECOLUMN>
<PAGECOLUMN></PAGECOLUMN>
<PAGECOLUMN></PAGECOLUMN>
<PAGECOLUMN>
<REGION>
<PARAGRAPH>
<LINE>
<WORD coords="1176,2112,1224,1960,2112">r</WORD>
<WORD coords="1440,2108,1492,1960,2108">r</WORD>
<WORD coords="1636,2124,1648,1952,2124">I</WORD>
<WORD coords="1764,2116,1812,1976,2116">r</WORD>
</LINE>
</PARAGRAPH>
</REGION>
</PAGECOLUMN>
<PAGECOLUMN>
<REGION>
<PARAGRAPH>
<LINE>
<WORD coords="2529,2320,2745,2277,2316">cresc.</WORD>
</LINE>
</PARAGRAPH>
</REGION>
</PAGECOLUMN>
<PAGECOLUMN>
<REGION>
<PARAGRAPH>
<LINE>
<WORD coords="1528,2616,1616,2468,2594">?5</WORD>
</LINE>
</PARAGRAPH>
</REGION>
</PAGECOLUMN>
<PAGECOLUMN>
<REGION>
<PARAGRAPH>
<LINE>
<WORD coords="567,2659,747,2584,2655">Give</WORD>
<WORD coords="867,2657,953,2613,2657">us</WORD>
<WORD coords="1051,2660,1160,2599,2659">tKc</WORD>
<WORD coords="1190,2684,1379,2593,2660">LigUt</WORD>
<WORD coords="1534,2658,1604,2602,2658">to</WORD>
<WORD coords="1738,2670,1862,2596,2664">live</WORD>
<WORD coords="1947,2664,2112,2596,2661">and</WORD>
<WORD coords="2151,2658,2289,2616,2657">cm.-</WORD>
<WORD coords="2309,2690,2425,2591,2659">jotj</WORD>
<WORD coords="2459,2659,2504,2650,2659">_</WORD>
</LINE>
</PARAGRAPH>
</REGION>
</PAGECOLUMN>
<PAGECOLUMN>
<REGION>
<PARAGRAPH>
<LINE>
<WORD coords="624,3108,632,2940,3108">I</WORD>
<WORD coords="860,3104,968,2892,3104">r</WORD>
<WORD coords="1088,3124,1316,2892,3084">pr</WORD>
<WORD coords="1540,3104,1824,2872,3084">fit</WORD>
<WORD coords="1976,3064,2060,2868,3064">t</WORD>
<WORD coords="2132,3076,3464,2812,3064">U-^i^^f</WORD>
</LINE>
</PARAGRAPH>
</REGION>
</PAGECOLUMN>
<PAGECOLUMN>
<REGION>
<PARAGRAPH>
<LINE>
<WORD coords="3660,2670,3800,2582,2661">Ike</WORD>
</LINE>
</PARAGRAPH>
</REGION>
</PAGECOLUMN>
<PAGECOLUMN></PAGECOLUMN>
<PAGECOLUMN>
<REGION>
<PARAGRAPH>
<LINE>
<WORD coords="558,4346,757,4285,4343">Lawn</WORD>
<WORD coords="1024,4363,1094,4295,4361">of</WORD>
<WORD coords="1154,4363,1193,4327,4363">a</WORD>
<WORD coords="1246,4368,1397,4296,4367">Tlftw</WORD>
<WORD coords="1517,4389,1669,4297,4362">Daij</WORD>
<WORD coords="1694,4365,1705,4290,4364">!</WORD>
<WORD coords="1746,4364,1796,4357,4364">_</WORD>
</LINE>
</PARAGRAPH>
</REGION>
</PAGECOLUMN>
</HIDDENTEXT>
</OBJECT>
<MAP name="Convention_0005.djvu"/>
<OBJECT data="file://localhost//t/derive/InauguralHymn1971ConstitutionalConvention//Inaugural Hymn 1971 Constitutional Convention.djvu" height="6040" type="image/x.djvu" usemap="Convention_0006.djvu" width="4248">
<PARAM name="PAGE" value="Convention_0006.djvu"/>
<PARAM name="DPI" value="600"/>
<HIDDENTEXT>
<PAGECOLUMN></PAGECOLUMN>
<PAGECOLUMN>
<REGION>
<PARAGRAPH>
<LINE>
<WORD coords="683,984,1147,940,983">TANGGAPAN</WORD>
<WORD coords="1182,985,1285,942,985">NG</WORD>
<WORD coords="1318,984,1640,939,982">KALIHIM</WORD>
</LINE>
</PARAGRAPH>
<PARAGRAPH>
<LINE>
<WORD coords="834,1044,999,1010,1043">OFFICC</WORD>
<WORD coords="1022,1045,1087,1012,1045">OF</WORD>
<WORD coords="1107,1045,1197,1011,1044">THE</WORD>
<WORD coords="1221,1045,1481,1010,1044">SECRETARY</WORD>
</LINE>
</PARAGRAPH>
</REGION>
</PAGECOLUMN>
<PAGECOLUMN>
<REGION>
<PARAGRAPH>
<LINE>
<WORD coords="1848,419,2256,365,418">REPUBLIKA</WORD>
<WORD coords="2314,421,2415,366,420">NG</WORD>
<WORD coords="2472,430,2816,370,426">PIUPINAS</WORD>
</LINE>
</PARAGRAPH>
<PARAGRAPH>
<LINE>
<WORD coords="1974,478,2190,443,476">REPUBUC</WORD>
<WORD coords="2213,476,2276,443,475">OP</WORD>
<WORD coords="2298,477,2385,443,476">THE</WORD>
<WORD coords="2411,483,2684,445,479">PHILIPPINES</WORD>
</LINE>
</PARAGRAPH>
<PARAGRAPH>
<LINE>
<WORD coords="1763,568,2230,512,565">KAGAWARAN</WORD>
<WORD coords="2288,565,2389,512,564">NG</WORD>
<WORD coords="2447,570,2894,515,568">EDUKASYON</WORD>
</LINE>
</PARAGRAPH>
<PARAGRAPH>
<LINE>
<WORD coords="1988,628,2291,590,625">DEPARTMENT</WORD>
<WORD coords="2313,625,2377,591,624">OF</WORD>
<WORD coords="2399,631,2667,593,629">EDUCATION</WORD>
</LINE>
</PARAGRAPH>
<PARAGRAPH>
<LINE>
<WORD coords="2168,700,2498,643,696">MAYNILA</WORD>
</LINE>
</PARAGRAPH>
<PARAGRAPH>
<LINE>
<WORD coords="2249,763,2428,725,761">MANILA</WORD>
</LINE>
</PARAGRAPH>
</REGION>
</PAGECOLUMN>
<PAGECOLUMN>
<REGION>
<PARAGRAPH>
<LINE>
<WORD coords="1474,1647,1602,1592,1647">Dr.</WORD>
<WORD coords="1667,1658,2051,1585,1642">Pajaro&apos;a</WORD>
<WORD coords="2111,1656,2636,1588,1642">composition</WORD>
<WORD coords="2688,1661,3070,1592,1652">pictures</WORD>
<WORD coords="3130,1659,3219,1602,1658">in</WORD>
</LINE>
<LINE>
<WORD coords="1028,1769,1313,1710,1767">soundB</WORD>
<WORD coords="1376,1766,1509,1708,1765">the</WORD>
<WORD coords="1568,1774,1856,1703,1760">coming</WORD>
<WORD coords="1913,1757,1999,1699,1756">of</WORD>
<WORD coords="2056,1754,2097,1712,1754">a</WORD>
<WORD coords="2157,1758,2344,1701,1755">dawn</WORD>
<WORD coords="2398,1761,2633,1702,1758">laden</WORD>
<WORD coords="2682,1766,2874,1707,1763">with</WORD>
<WORD coords="2933,1772,3065,1709,1768">the</WORD>
<WORD coords="3125,1785,3455,1718,1775">promise</WORD>
</LINE>
<LINE>
<WORD coords="1026,1872,1114,1814,1871">of</WORD>
<WORD coords="1169,1870,1212,1827,1870">a</WORD>
<WORD coords="1269,1872,1413,1827,1870">new</WORD>
<WORD coords="1471,1880,1609,1812,1867">day</WORD>
<WORD coords="1668,1864,1807,1806,1863">for</WORD>
<WORD coords="1867,1861,2005,1818,1860">our</WORD>
<WORD coords="2060,1873,2381,1802,1859">people.</WORD>
<WORD coords="2493,1880,2727,1804,1863">Every</WORD>
<WORD coords="2783,1889,3201,1810,1869">Filipino,</WORD>
</LINE>
<LINE>
<WORD coords="1023,1993,1268,1935,1977">young</WORD>
<WORD coords="1321,1974,1466,1918,1973">and</WORD>
<WORD coords="1524,1981,1695,1914,1970">old,</WORD>
<WORD coords="1768,1967,2056,1907,1965">should</WORD>
<WORD coords="2110,1962,2346,1904,1961">learn</WORD>
<WORD coords="2404,1963,2486,1907,1962">to</WORD>
<WORD coords="2547,1984,2730,1910,1966">sing</WORD>
<WORD coords="2790,1972,2920,1914,1970">the</WORD>
<WORD coords="2985,1980,3361,1916,1975">official</WORD>
</LINE>
<LINE>
<WORD coords="1017,2106,1219,2037,2091">hymn</WORD>
<WORD coords="1273,2090,1360,2033,2089">of</WORD>
<WORD coords="1420,2088,1556,2034,2087">the</WORD>
<WORD coords="1615,2093,1803,2028,2088">1971</WORD>
<WORD coords="1862,2088,2531,2028,2084">Constitutional</WORD>
<WORD coords="2591,2098,3102,2032,2093">Convention.</WORD>
<WORD coords="3220,2103,3356,2044,2101">Let</WORD>
</LINE>
<LINE>
<WORD coords="1022,2215,1164,2174,2214">our</WORD>
<WORD coords="1221,2212,1608,2158,2211">children</WORD>
<WORD coords="1665,2220,1849,2154,2206">sing</WORD>
<WORD coords="1912,2204,1993,2151,2203">it</WORD>
<WORD coords="2051,2203,2244,2148,2202">with</WORD>
<WORD coords="2301,2204,2438,2163,2203">our</WORD>
<WORD coords="2491,2212,2868,2154,2207">national</WORD>
<WORD coords="2927,2217,3215,2161,2213">anthem</WORD>
</LINE>
<LINE>
<WORD coords="1024,2349,1311,2282,2337">during</WORD>
<WORD coords="1372,2333,1504,2281,2332">the</WORD>
<WORD coords="1565,2340,1753,2274,2327">flag</WORD>
<WORD coords="1811,2336,2193,2284,2324">ceremony</WORD>
<WORD coords="2256,2322,2341,2269,2322">in</WORD>
<WORD coords="2401,2326,2536,2284,2324">our</WORD>
<WORD coords="2592,2334,2958,2278,2331">schools.</WORD>
</LINE>
</PARAGRAPH>
</REGION>
</PAGECOLUMN>
<PAGECOLUMN>
<REGION>
<PARAGRAPH>
<LINE>
<WORD coords="2348,2700,2680,2632,2697">NJfRCISO</WORD>
<WORD coords="2731,2704,3148,2632,2702">AtSARRAC]</WORD>
</LINE>
<LINE>
<WORD coords="2445,2797,3115,2718,2780">Undersecretary</WORD>
</LINE>
</PARAGRAPH>
</REGION>
</PAGECOLUMN>
<PAGECOLUMN></PAGECOLUMN>
<PAGECOLUMN></PAGECOLUMN>
<PAGECOLUMN>
<REGION>
<PARAGRAPH>
<LINE>
<WORD coords="1846,3452,2256,3395,3448">REPUBLIKA</WORD>
<WORD coords="2316,3444,2415,3392,3444">NG</WORD>
<WORD coords="2475,3447,2820,3392,3444">PILIPINAS</WORD>
</LINE>
</PARAGRAPH>
<PARAGRAPH>
<LINE>
<WORD coords="1971,3510,2189,3472,3507">REPUBLIC</WORD>
<WORD coords="2213,3504,2275,3471,3503">OF</WORD>
<WORD coords="2299,3502,2385,3469,3501">THE</WORD>
<WORD coords="2412,3501,2686,3468,3498">PHILIPPINES</WORD>
</LINE>
</PARAGRAPH>
<PARAGRAPH>
<LINE>
<WORD coords="1759,3608,2227,3543,3600">KAGAWARAN</WORD>
<WORD coords="2287,3592,2386,3539,3591">NG</WORD>
<WORD coords="2449,3590,2896,3535,3588">EDUKASYON</WORD>
</LINE>
</PARAGRAPH>
<PARAGRAPH>
<LINE>
<WORD coords="1983,3663,2288,3620,3658">DEPARTMENT</WORD>
<WORD coords="2312,3653,2374,3619,3652">OF</WORD>
<WORD coords="2398,3651,2667,3616,3650">EDUCATION</WORD>
</LINE>
</PARAGRAPH>
<PARAGRAPH>
<LINE>
<WORD coords="2163,3728,2495,3672,3726">MAYNILA</WORD>
</LINE>
</PARAGRAPH>
<PARAGRAPH>
<LINE>
<WORD coords="2244,3792,2424,3754,3790">MANILA</WORD>
</LINE>
</PARAGRAPH>
</REGION>
</PAGECOLUMN>
<PAGECOLUMN>
<REGION>
<PARAGRAPH>
<LINE>
<WORD coords="668,4050,1137,4003,4047">TANGGAPAN</WORD>
<WORD coords="1170,4044,1275,4001,4043">NG</WORD>
<WORD coords="1308,4040,1631,3993,4037">KALIHIM</WORD>
</LINE>
</PARAGRAPH>
<PARAGRAPH>
<LINE>
<WORD coords="824,4108,986,4074,4106">OFFICE</WORD>
<WORD coords="1010,4107,1074,4074,4106">OF</WORD>
<WORD coords="1096,4105,1184,4072,4104">THE</WORD>
<WORD coords="1210,4104,1469,4065,4101">SECRETARY</WORD>
</LINE>
</PARAGRAPH>
</REGION>
</PAGECOLUMN>
<PAGECOLUMN>
<REGION>
<PARAGRAPH>
<LINE>
<WORD coords="1301,4514,1436,4457,4512">Let</WORD>
<WORD coords="1501,4508,1585,4468,4507">US</WORD>
<WORD coords="1652,4507,1885,4451,4503">teach</WORD>
<WORD coords="1949,4497,2079,4447,4496">tiie</WORD>
<WORD coords="2142,4493,2812,4430,4488">Constitutional</WORD>
<WORD coords="2872,4497,3355,4431,4490">Convention</WORD>
</LINE>
<LINE>
<WORD coords="994,4651,1191,4583,4636">Hymn</WORD>
<WORD coords="1252,4631,1334,4579,4630">to</WORD>
<WORD coords="1401,4628,1540,4586,4627">our</WORD>
<WORD coords="1597,4637,1880,4566,4622">pupiis</WORD>
<WORD coords="1938,4615,2083,4560,4614">and</WORD>
<WORD coords="2141,4612,2557,4555,4609">students.</WORD>
<WORD coords="2670,4616,2904,4548,4602">Every</WORD>
<WORD coords="2960,4608,3155,4553,4605">word</WORD>
<WORD coords="3216,4609,3297,4554,4608">of</WORD>
<WORD coords="3366,4619,3496,4562,4615">the</WORD>
</LINE>
<LINE>
<WORD coords="990,4767,1188,4701,4751">hymn</WORD>
<WORD coords="1249,4746,1334,4690,4746">is</WORD>
<WORD coords="1395,4742,1581,4682,4740">full</WORD>
<WORD coords="1645,4737,1729,4678,4736">of</WORD>
<WORD coords="1793,4746,2410,4667,4724">significance.</WORD>
<WORD coords="2525,4714,2658,4658,4713">The</WORD>
<WORD coords="2716,4725,3003,4657,4712">melody</WORD>
<WORD coords="3058,4717,3198,4661,4714">has</WORD>
<WORD coords="3259,4733,3649,4668,4722">captured</WORD>
</LINE>
<LINE>
<WORD coords="995,4887,1129,4831,4886">the</WORD>
<WORD coords="1196,4883,1536,4816,4875">emotion</WORD>
<WORD coords="1596,4870,1777,4812,4867">that</WORD>
<WORD coords="1840,4869,2075,4814,4860">every</WORD>
<WORD coords="2134,4865,2415,4794,4850">single</WORD>
<WORD coords="2473,4860,2752,4790,4841">phrase</WORD>
<WORD coords="2815,4839,2898,4783,4838">of</WORD>
<WORD coords="2964,4843,3095,4787,4841">the</WORD>
<WORD coords="3161,4845,3342,4789,4843">text</WORD>
<WORD coords="3405,4852,3641,4798,4851">seeks</WORD>
</LINE>
<LINE>
<WORD coords="996,5009,1082,4950,5008">to</WORD>
<WORD coords="1145,5009,1472,4952,4999">convey.</WORD>
<WORD coords="1593,4991,1728,4934,4990">Let</WORD>
<WORD coords="1793,4985,1877,4943,4984">us</WORD>
<WORD coords="1933,4981,2122,4927,4978">have</WORD>
<WORD coords="2188,4975,2323,4932,4974">our</WORD>
<WORD coords="2380,4969,2758,4912,4966">children</WORD>
<WORD coords="2816,4977,3003,4907,4960">sing</WORD>
<WORD coords="3067,4965,3148,4910,4965">it</WORD>
<WORD coords="3211,4971,3400,4909,4968">from</WORD>
</LINE>
<LINE>
<WORD coords="986,5133,1282,5077,5124">memory</WORD>
<WORD coords="1338,5113,1534,5056,5112">with</WORD>
<WORD coords="1592,5109,1771,5049,5108">full</WORD>
<WORD coords="1839,5104,2467,5032,5095">understanding</WORD>
<WORD coords="2524,5084,2605,5023,5083">of</WORD>
<WORD coords="2670,5080,2799,5024,5079">its</WORD>
<WORD coords="2858,5099,3197,5025,5078">aeaning</WORD>
<WORD coords="3254,5106,3545,5027,5086">during</WORD>
</LINE>
<LINE>
<WORD coords="993,5254,1126,5196,5253">the</WORD>
<WORD coords="1191,5259,1381,5189,5244">flag</WORD>
<WORD coords="1435,5250,1865,5191,5241">ceremony.</WORD>
</LINE>
</PARAGRAPH>
</REGION>
</PAGECOLUMN>
<PAGECOLUMN>
<REGION>
<PARAGRAPH>
<LINE>
<WORD coords="2178,5628,3055,5491,5607">LIGERjTlRlLMt^</WORD>
<WORD coords="3106,5592,3440,5536,5591">SORIANO</WORD>
</LINE>
<LINE>
<WORD coords="2180,5685,2561,5626,5681">Director</WORD>
<WORD coords="2619,5673,2702,5614,5671">of</WORD>
<WORD coords="2765,5665,3042,5605,5660">Public</WORD>
<WORD coords="3109,5661,3440,5602,5658">Schools</WORD>
</LINE>
</PARAGRAPH>
</REGION>
</PAGECOLUMN>
</HIDDENTEXT>
</OBJECT>
<MAP name="Convention_0006.djvu"/>
<OBJECT data="file://localhost//t/derive/InauguralHymn1971ConstitutionalConvention//Inaugural Hymn 1971 Constitutional Convention.djvu" height="6008" type="image/x.djvu" usemap="Convention_0007.djvu" width="4254">
<PARAM name="PAGE" value="Convention_0007.djvu"/>
<PARAM name="DPI" value="600"/>
<HIDDENTEXT>
<PAGECOLUMN></PAGECOLUMN>
<PAGECOLUMN>
<REGION>
<PARAGRAPH>
<LINE>
<WORD coords="1883,441,2293,381,438">RE?UBL1KA</WORD>
<WORD coords="2349,436,2454,381,436">NG</WORD>
<WORD coords="2510,437,2862,381,436">PIUPINAS</WORD>
</LINE>
</PARAGRAPH>
<PARAGRAPH>
<LINE>
<WORD coords="2007,500,2225,461,496">REPUBLIC</WORD>
<WORD coords="2246,495,2313,460,494">OP</WORD>
<WORD coords="2334,494,2423,459,493">THE</WORD>
<WORD coords="2447,494,2726,459,492">PHILIPPINES</WORD>
</LINE>
</PARAGRAPH>
<PARAGRAPH>
<LINE>
<WORD coords="1795,596,2264,530,589">KAGAWARAN</WORD>
<WORD coords="2321,584,2426,530,584">NG</WORD>
<WORD coords="2482,583,2940,526,582">EDUKASYON</WORD>
</LINE>
</PARAGRAPH>
<PARAGRAPH>
<LINE>
<WORD coords="2018,651,2325,609,647">OEPAtTMSNT</WORD>
<WORD coords="2347,645,2412,610,645">OP</WORD>
<WORD coords="2433,647,2708,607,645">EDUCATION</WORD>
</LINE>
</PARAGRAPH>
<PARAGRAPH>
<LINE>
<WORD coords="2197,719,2534,663,718">MAYNILA</WORD>
</LINE>
</PARAGRAPH>
<PARAGRAPH>
<LINE>
<WORD coords="2278,782,2461,745,781">MANILA</WORD>
</LINE>
</PARAGRAPH>
</REGION>
</PAGECOLUMN>
<PAGECOLUMN>
<REGION>
<PARAGRAPH>
<LINE>
<WORD coords="735,1005,1186,963,1003">TANCGAPAN</WORD>
<WORD coords="1218,1004,1319,963,1004">NG</WORD>
<WORD coords="1349,1002,1668,958,1001">KALJHIM</WORD>
</LINE>
</PARAGRAPH>
<PARAGRAPH>
<LINE>
<WORD coords="880,1062,1039,1028,1061">OPPlCfi</WORD>
<WORD coords="1062,1062,1126,1029,1062">OP</WORD>
<WORD coords="1144,1063,1232,1028,1062">THE</WORD>
<WORD coords="1256,1062,1509,1026,1061">SECRETARY</WORD>
</LINE>
</PARAGRAPH>
</REGION>
</PAGECOLUMN>
<PAGECOLUMN>
<REGION>
<PARAGRAPH>
<LINE>
<WORD coords="2642,1179,2717,1085,1179">Y</WORD>
</LINE>
</PARAGRAPH>
</REGION>
</PAGECOLUMN>
<PAGECOLUMN>
<REGION>
<PARAGRAPH>
<LINE>
<WORD coords="1318,1698,1494,1636,1697">&quot;The</WORD>
<WORD coords="1554,1696,1748,1638,1695">Dawn</WORD>
<WORD coords="1805,1696,1892,1637,1695">of</WORD>
<WORD coords="1948,1694,1990,1651,1694">a</WORD>
<WORD coords="2051,1696,2191,1637,1694">New</WORD>
<WORD coords="2244,1704,2428,1628,1690">Day&quot;</WORD>
<WORD coords="2495,1687,2581,1628,1687">is</WORD>
<WORD coords="2636,1683,2734,1639,1682">an</WORD>
<WORD coords="2793,1694,3179,1622,1680">inopired</WORD>
</LINE>
<LINE>
<WORD coords="1020,1829,1602,1757,1815">aupplication</WORD>
<WORD coords="1652,1816,2095,1756,1814">addressed</WORD>
<WORD coords="2152,1810,2239,1754,1809">to</WORD>
<WORD coords="2302,1808,2435,1752,1807">the</WORD>
<WORD coords="2495,1805,2679,1745,1803">Most</WORD>
<WORD coords="2735,1814,2933,1741,1800">Hi^</WORD>
<WORD coords="2992,1809,3079,1740,1796">by</WORD>
<WORD coords="3133,1794,3175,1751,1794">a</WORD>
<WORD coords="3229,1806,3566,1729,1789">hopeful</WORD>
</LINE>
<LINE>
<WORD coords="1010,1946,1334,1875,1932">people.</WORD>
<WORD coords="1457,1929,1542,1872,1928">It</WORD>
<WORD coords="1606,1930,1691,1873,1929">is</WORD>
<WORD coords="1753,1928,2086,1871,1926">intense</WORD>
<WORD coords="2143,1922,2290,1866,1921">and</WORD>
<WORD coords="2347,1920,2676,1856,1916">earnest</WORD>
<WORD coords="2742,1910,2830,1854,1910">in</WORD>
<WORD coords="2888,1908,3071,1850,1906">text</WORD>
<WORD coords="3129,1904,3274,1847,1903">and</WORD>
<WORD coords="3333,1901,3554,1846,1900">tune.</WORD>
</LINE>
<LINE>
<WORD coords="1015,2073,1103,2006,2060">By</WORD>
<WORD coords="1159,2061,1300,2004,2060">all</WORD>
<WORD coords="1357,2061,1595,2018,2059">means</WORD>
<WORD coords="1617,2072,1634,2041,2060">p</WORD>
<WORD coords="1703,2060,1842,2001,2058">let</WORD>
<WORD coords="1905,2057,1991,2016,2057">us</WORD>
<WORD coords="2047,2055,2237,2001,2053">have</WORD>
<WORD coords="2300,2049,2439,2007,2048">our</WORD>
<WORD coords="2493,2058,2734,2004,2044">young</WORD>
<WORD coords="2788,2056,3074,1984,2039">people</WORD>
<WORD coords="3133,2036,3375,1980,2033">learn</WORD>
<WORD coords="3432,2031,3517,1977,2031">to</WORD>
</LINE>
<LINE>
<WORD coords="1015,2188,1203,2118,2172">sing</WORD>
<WORD coords="1264,2171,1348,2116,2171">it</WORD>
<WORD coords="1412,2184,1498,2117,2171">by</WORD>
<WORD coords="1552,2171,1799,2115,2170">heart</WORD>
<WORD coords="1857,2182,2242,2112,2166">together</WORD>
<WORD coords="2294,2161,2490,2104,2160">with</WORD>
<WORD coords="2547,2157,2685,2115,2156">our</WORD>
<WORD coords="2739,2153,3128,2092,2150">national</WORD>
<WORD coords="3180,2145,3474,2088,2144">anthem</WORD>
</LINE>
<LINE>
<WORD coords="1017,2288,1304,2216,2273">during</WORD>
<WORD coords="1364,2271,1497,2215,2271">the</WORD>
<WORD coords="1561,2285,1750,2213,2268">flag</WORD>
<WORD coords="1806,2279,2191,2224,2268">ceremony</WORD>
<WORD coords="2253,2262,2343,2207,2262">in</WORD>
<WORD coords="2401,2260,2540,2217,2259">our</WORD>
<WORD coords="2596,2257,2971,2197,2254">schools.</WORD>
</LINE>
</PARAGRAPH>
</REGION>
</PAGECOLUMN>
<PAGECOLUMN>
<REGION>
<PARAGRAPH>
<LINE>
<WORD coords="2045,2766,2197,2662,2758">X\</WORD>
<WORD coords="2203,2750,2497,2686,2747">JULIAN</WORD>
<WORD coords="2551,2744,2631,2687,2744">B.</WORD>
<WORD coords="2698,2742,2988,2678,2740">YBALLE</WORD>
</LINE>
<LINE>
<WORD coords="2106,2850,2497,2746,2821">U^l^ector</WORD>
<WORD coords="2555,2817,2638,2759,2816">of</WORD>
<WORD coords="2699,2815,3032,2756,2812">Private</WORD>
<WORD coords="3094,2807,3427,2746,2802">Schools</WORD>
</LINE>
</PARAGRAPH>
</REGION>
</PAGECOLUMN>
<PAGECOLUMN></PAGECOLUMN>
<PAGECOLUMN>
<REGION>
<PARAGRAPH>
<LINE>
<WORD coords="1902,3472,2318,3411,3467">REPUBLIKA</WORD>
<WORD coords="2376,3463,2481,3409,3462">NG</WORD>
<WORD coords="2538,3460,2892,3405,3459">PIUPINAS</WORD>
</LINE>
</PARAGRAPH>
<PARAGRAPH>
<LINE>
<WORD coords="2030,3530,2251,3490,3526">REPUBUC</WORD>
<WORD coords="2273,3523,2339,3489,3522">OP</WORD>
<WORD coords="2360,3521,2449,3486,3520">THE</WORD>
<WORD coords="2475,3518,2758,3482,3516">PHILIPPINES</WORD>
</LINE>
</PARAGRAPH>
<PARAGRAPH>
<LINE>
<WORD coords="1815,3626,2291,3559,3618">KAGAWARAN</WORD>
<WORD coords="2350,3610,2455,3555,3609">NG</WORD>
<WORD coords="2512,3606,2971,3545,3602">EDUKASYON</WORD>
</LINE>
</PARAGRAPH>
<PARAGRAPH>
<LINE>
<WORD coords="2043,3680,2354,3637,3676">DEPARTMENT</WORD>
<WORD coords="2376,3671,2441,3635,3670">OP</WORD>
<WORD coords="2464,3669,2740,3629,3667">EDUCATION</WORD>
</LINE>
</PARAGRAPH>
<PARAGRAPH>
<LINE>
<WORD coords="2226,3747,2567,3687,3744">MAYNILA</WORD>
</LINE>
</PARAGRAPH>
<PARAGRAPH>
<LINE>
<WORD coords="2310,3809,2495,3770,3807">MANILA</WORD>
</LINE>
</PARAGRAPH>
</REGION>
</PAGECOLUMN>
<PAGECOLUMN>
<REGION>
<PARAGRAPH>
<LINE>
<WORD coords="736,4047,1198,3999,4043">TANGGAPAN</WORD>
<WORD coords="1230,4047,1334,4003,4047">NG</WORD>
<WORD coords="1367,4046,1694,3999,4043">KALIHIM</WORD>
</LINE>
</PARAGRAPH>
<PARAGRAPH>
<LINE>
<WORD coords="887,4104,1049,4069,4101">OFPiCe</WORD>
<WORD coords="1072,4106,1137,4073,4105">OP</WORD>
<WORD coords="1156,4106,1246,4071,4105">THE</WORD>
<WORD coords="1269,4107,1533,4069,4105">SECRETARY</WORD>
</LINE>
</PARAGRAPH>
</REGION>
</PAGECOLUMN>
<PAGECOLUMN>
<REGION>
<PARAGRAPH>
<LINE>
<WORD coords="1471,4711,1715,4650,4706">Learn</WORD>
<WORD coords="1772,4701,1856,4641,4700">to</WORD>
<WORD coords="1920,4713,2109,4638,4698">sing</WORD>
<WORD coords="2169,4699,2352,4638,4698">&quot;The</WORD>
<WORD coords="2410,4697,2604,4637,4694">Dawn</WORD>
<WORD coords="2660,4697,2746,4637,4697">of</WORD>
<WORD coords="2802,4695,2843,4651,4695">a</WORD>
<WORD coords="2906,4700,3048,4639,4697">New</WORD>
<WORD coords="3104,4710,3287,4633,4695">Day.**</WORD>
</LINE>
<LINE>
<WORD coords="1030,4815,1169,4754,4812">The</WORD>
<WORD coords="1230,4835,1661,4761,4816">religious</WORD>
<WORD coords="1717,4816,1865,4757,4814">and</WORD>
<WORD coords="1916,4827,2351,4753,4811">patriotic</WORD>
<WORD coords="2413,4812,2703,4749,4809">fervor</WORD>
<WORD coords="2760,4812,2847,4752,4811">of</WORD>
<WORD coords="2911,4813,3044,4754,4812">the</WORD>
<WORD coords="3103,4811,3343,4753,4809">wards</WORD>
<WORD coords="3398,4810,3545,4753,4808">and</WORD>
</LINE>
<LINE>
<WORD coords="1037,4926,1218,4867,4923">tune</WORD>
<WORD coords="1280,4930,1363,4872,4929">of</WORD>
<WORD coords="1428,4933,1561,4875,4932">the</WORD>
<WORD coords="1618,4944,1814,4875,4931">hymn</WORD>
<WORD coords="1862,4932,2152,4872,4931">voices</WORD>
<WORD coords="2215,4935,2350,4875,4933">the</WORD>
<WORD coords="2413,4940,2846,4877,4935">sentiment</WORD>
<WORD coords="2911,4939,2997,4880,4939">of</WORD>
<WORD coords="3057,4938,3199,4894,4937">our</WORD>
<WORD coords="3252,4952,3539,4878,4937">people</WORD>
</LINE>
<LINE>
<WORD coords="1034,5041,1122,4998,5040">on</WORD>
<WORD coords="1182,5052,1363,4988,5048">this</WORD>
<WORD coords="1420,5053,1856,4997,5051">momentous</WORD>
<WORD coords="1921,5053,2340,4994,5050">occasion.</WORD>
<WORD coords="2462,5052,2603,4991,5051">Our</WORD>
<WORD coords="2662,5053,2946,4993,5051">school</WORD>
<WORD coords="3008,5050,3398,4989,5048">children</WORD>
<WORD coords="3451,5051,3598,4990,5048">and</WORD>
</LINE>
<LINE>
<WORD coords="1042,5170,1178,5122,5167">our</WORD>
<WORD coords="1231,5187,1519,5123,5179">youths</WORD>
<WORD coords="1579,5186,1870,5127,5184">should</WORD>
<WORD coords="1926,5184,2009,5127,5183">be</WORD>
<WORD coords="2067,5186,2255,5128,5184">able</WORD>
<WORD coords="2320,5185,2403,5130,5184">to</WORD>
<WORD coords="2467,5198,2657,5128,5184">sing</WORD>
<WORD coords="2716,5186,2802,5128,5184">it</WORD>
<WORD coords="2867,5201,2951,5131,5188">by</WORD>
<WORD coords="3003,5188,3286,5128,5186">heart.</WORD>
</LINE>
</PARAGRAPH>
</REGION>
</PAGECOLUMN>
<PAGECOLUMN></PAGECOLUMN>
<PAGECOLUMN>
<REGION>
<PARAGRAPH>
<LINE>
<WORD coords="2867,5662,2912,5603,5663">1</WORD>
<WORD coords="2964,5665,3408,5603,5659">Education</WORD>
</LINE>
</PARAGRAPH>
</REGION>
</PAGECOLUMN>
</HIDDENTEXT>
</OBJECT>
<MAP name="Convention_0007.djvu"/>
</BODY>
</DjVuXML>
