<?xml version="1.0" encoding="UTF-8"?>
<metadata>
  <identifier>JointPreparatoryCommiteeOnPhilippineAffairs</identifier>
  <mediatype>texts</mediatype>
  <date>1938</date>
  <description>This document includes reports prepared by the Joint Preparatory Committee on Philippine Affairs on areas such as trade relations, finance, and economic adjustment.</description>
  <language>eng</language>
  <licenseurl>http://creativecommons.org/publicdomain/mark/1.0/</licenseurl>
  <scanner>Internet Archive HTML5 Uploader 1.6.1</scanner>
  <subject>Manuel L. Quezon</subject>
  <title>Joint Preparatory Commitee On Philippine Affairs</title>
  <publicdate>2015-05-14 07:47:37</publicdate>
  <uploader>cheng.bigay@pcdspo.gov.ph</uploader>
  <addeddate>2015-05-14 07:47:37</addeddate>
  <curation>[curator]validator@archive.org[/curator][date]20150514074955[/date][comment]checked for malware[/comment]</curation>
  <identifier-access>http://archive.org/details/JointPreparatoryCommiteeOnPhilippineAffairs</identifier-access>
  <identifier-ark>ark:/13960/t5v72w109</identifier-ark>
  <ppi>600</ppi>
  <ocr>ABBYY FineReader 9.0</ocr>
  <repub_state>4</repub_state>
  <year>1938</year>
  <collection>presidentmanuelquezon</collection>
  <collection>presidentialmuseumandlibrary</collection>
  <collection>additional_collections</collection>
  <backup_location>ia905305_22</backup_location>
</metadata>
