<?xml version="1.0" encoding="UTF-8"?>
<metadata>
  <identifier>TheFilipinoPeople</identifier>
  <mediatype>texts</mediatype>
  <collection>presidentialmuseumandlibrary</collection>
  <date>1916-08</date>
  <description>The Filipino People&lt;div&gt;August 1916&lt;/div&gt;</description>
  <scanner>Internet Archive HTML5 Uploader 1.6.1</scanner>
  <subject>Magazine</subject>
  <title>The Filipino People</title>
  <publicdate>2015-05-14 09:52:58</publicdate>
  <uploader>cheng.bigay@pcdspo.gov.ph</uploader>
  <addeddate>2015-05-14 09:52:58</addeddate>
  <curation>[curator]validator@archive.org[/curator][date]20150514100203[/date][comment]checked for malware[/comment]</curation>
  <language>English</language>
  <identifier-access>http://archive.org/details/TheFilipinoPeople</identifier-access>
  <identifier-ark>ark:/13960/t5z63zp8g</identifier-ark>
  <ppi>600</ppi>
  <ocr>ABBYY FineReader 9.0</ocr>
  <repub_state>4</repub_state>
  <collection>additional_collections</collection>
  <backup_location>ia905305_22</backup_location>
</metadata>
