<?xml version="1.0" encoding="UTF-8"?>
<metadata>
  <identifier>PhilippinesVol1No6</identifier>
  <mediatype>texts</mediatype>
  <collection>presidentialmuseumandlibrary</collection>
  <description>This issue of the Philippines Magazine includes speech of President Manuel L. Quezon on Philippine loyalty and articles on Philippine trade, Manuel Roxas and Manila’s position in a changing Asia among other</description>
  <language>eng</language>
  <licenseurl>http://creativecommons.org/licenses/by/4.0/</licenseurl>
  <scanner>Internet Archive HTML5 Uploader 1.6.1</scanner>
  <subject>Magazine</subject>
  <title>Philippines Magazine Vol. 1 No. 6 (August 1941)</title>
  <publicdate>2015-05-13 06:26:41</publicdate>
  <uploader>cheng.bigay@pcdspo.gov.ph</uploader>
  <addeddate>2015-05-13 06:26:41</addeddate>
  <curation>[curator]validator@archive.org[/curator][date]20150513063725[/date][comment]checked for malware[/comment]</curation>
  <identifier-access>http://archive.org/details/PhilippinesVol1No6</identifier-access>
  <identifier-ark>ark:/13960/t0xq0fb9m</identifier-ark>
  <ppi>600</ppi>
  <ocr>ABBYY FineReader 9.0</ocr>
  <repub_state>4</repub_state>
  <collection>additional_collections</collection>
  <date>1941-08</date>
  <year>1941</year>
  <backup_location>ia905305_20</backup_location>
</metadata>
