<?xml version="1.0" encoding="UTF-8"?>
<!DOCTYPE DjVuXML>
<DjVuXML>
<BODY>
<OBJECT data="file://localhost//tmp/derive/letter-from-basiliio-valdes-unidentified-gentleman-june-26-1934//BVC-0398-062634-CP.djvu" height="6315" type="image/x.djvu" usemap="BVC-0398-062634-CP_0000.djvu" width="4785">
<PARAM name="PAGE" value="BVC-0398-062634-CP_0000.djvu"/>
<PARAM name="DPI" value="600"/>
<HIDDENTEXT>
<PAGECOLUMN>
<REGION backgroundColor="11371604" orientation="RotatedCounterclockwise">
<PARAGRAPH>
<LINE>
<WORD coords="2,3260,66,3190,3260">v</WORD>
</LINE>
</PARAGRAPH>
</REGION>
</PAGECOLUMN>
<PAGECOLUMN></PAGECOLUMN>
<PAGECOLUMN>
<REGION backgroundColor="12954488">
<PARAGRAPH>
<LINE>
<WORD coords="655,1573,769,1499,1572">to</WORD>
<WORD coords="843,1577,1073,1501,1575">tell</WORD>
<WORD coords="1141,1595,1319,1523,1582">you</WORD>
<WORD coords="1377,1583,1555,1511,1583">how</WORD>
</LINE>
<LINE>
<WORD coords="649,1697,1191,1599,1678">privilege</WORD>
<WORD coords="1259,1699,1437,1627,1683">you</WORD>
<WORD coords="1495,1687,1725,1611,1685">have</WORD>
</LINE>
<LINE>
<WORD coords="651,1787,887,1719,1774">your</WORD>
<WORD coords="951,1795,1255,1711,1777">party</WORD>
<WORD coords="1309,1801,1677,1709,1784">during</WORD>
</LINE>
</PARAGRAPH>
<PARAGRAPH>
<LINE>
<WORD coords="653,1881,995,1801,1876">couth*</WORD>
<WORD coords="1137,1881,1243,1807,1880">It</WORD>
<WORD coords="1313,1883,1485,1811,1881">has</WORD>
<WORD coords="1553,1887,1789,1813,1885">been</WORD>
<WORD coords="1853,1889,1909,1835,1889">a</WORD>
<WORD coords="2013,1919,2103,1885,1910">^</WORD>
<WORD coords="2703,1907,2749,1885,1907">^</WORD>
</LINE>
</PARAGRAPH>
<PARAGRAPH>
<LINE>
<WORD coords="647,1977,885,1903,1976">rich</WORD>
<WORD coords="955,1981,1065,1907,1981">in</WORD>
<WORD coords="1131,2013,1833,1911,1986">©xpoF.lc-.nces,</WORD>
<WORD coords="1909,1993,2103,1885,1993">enT</WORD>
<WORD coords="2151,2001,2375,1885,2000">has&quot;</WORD>
<WORD coords="2395,2007,2669,1891,2006">been”</WORD>
<WORD coords="2689,2013,2921,1941,2012">most</WORD>
</LINE>
<LINE>
<WORD coords="651,2085,1299,1999,2081">instructive</WORD>
<WORD coords="1369,2087,1541,2017,2086">and</WORD>
<WORD coords="1609,2119,2335,2019,2095">enlightening</WORD>
<WORD coords="2399,2105,2509,2033,2105">to</WORD>
<WORD coords="2565,2113,2687,2055,2111">me</WORD>
<WORD coords="2755,2115,2985,2041,2113">both</WORD>
</LINE>
<LINE>
<WORD coords="651,2177,759,2123,2176">as</WORD>
<WORD coords="831,2179,883,2125,2179">a</WORD>
<WORD coords="953,2201,1541,2119,2187">government</WORD>
<WORD coords="1615,2199,2085,2121,2194">official</WORD>
<WORD coords="2155,2203,2329,2131,2201">and</WORD>
<WORD coords="2399,2207,2453,2149,2207">a</WORD>
<WORD coords="2517,2219,2923,2133,2213">private</WORD>
</LINE>
<LINE>
<WORD coords="645,2287,1107,2201,2280">citizen.</WORD>
</LINE>
</PARAGRAPH>
</REGION>
</PAGECOLUMN>
<PAGECOLUMN>
<REGION backgroundColor="12954490">
<PARAGRAPH>
<LINE>
<WORD coords="2405,1499,2585,1425,1497">few</WORD>
<WORD coords="2647,1503,2935,1427,1501">lines</WORD>
</LINE>
<LINE>
<WORD coords="2351,1603,2637,1523,1601">date</WORD>
<WORD coords="2707,1605,2875,1531,1603">the</WORD>
</LINE>
<LINE>
<WORD coords="2151,1693,2271,1639,1693">me</WORD>
<WORD coords="2345,1699,2459,1619,1698">in</WORD>
<WORD coords="2527,1725,2937,1627,1705">joining</WORD>
</LINE>
<LINE>
<WORD coords="2163,1793,2269,1719,1793">it</WORD>
<WORD coords="2341,1797,2455,1727,1797">to</WORD>
<WORD coords="2525,1801,2691,1729,1799">the</WORD>
</LINE>
</PARAGRAPH>
<PARAGRAPH>
<LINE>
<WORD coords="2577,1927,2853,1831,1903">trip,</WORD>
</LINE>
</PARAGRAPH>
</REGION>
</PAGECOLUMN>
<PAGECOLUMN>
<REGION backgroundColor="13085044">
<PARAGRAPH>
<LINE>
<WORD coords="1817,487,2221,387,462">MANILA,</WORD>
<WORD coords="2301,475,2533,399,473">June</WORD>
<WORD coords="2601,500,2763,407,489">26,</WORD>
<WORD coords="2841,491,3075,409,487">1934</WORD>
</LINE>
</PARAGRAPH>
</REGION>
</PAGECOLUMN>
<PAGECOLUMN>
<REGION backgroundColor="12228453">
<PARAGRAPH>
<LINE>
<WORD coords="3052,452,3324,124,452">*</WORD>
</LINE>
</PARAGRAPH>
</REGION>
</PAGECOLUMN>
<PAGECOLUMN>
<REGION backgroundColor="10977880">
<PARAGRAPH></PARAGRAPH>
</REGION>
</PAGECOLUMN>
<PAGECOLUMN></PAGECOLUMN>
<PAGECOLUMN>
<REGION backgroundColor="13744008">
<PARAGRAPH>
<LINE>
<WORD coords="1003,2515,1475,2411,2491">However,</WORD>
<WORD coords="1555,2495,1601,2425,2495">I</WORD>
<WORD coords="1673,2503,1903,2425,2499">feel</WORD>
<WORD coords="1969,2505,2197,2431,2504">that</WORD>
<WORD coords="2269,2509,2443,2435,2508">the</WORD>
<WORD coords="2517,2531,2977,2447,2517">greatest</WORD>
</LINE>
<LINE>
<WORD coords="639,2587,885,2509,2584">boon</WORD>
<WORD coords="947,2589,1175,2515,2588">that</WORD>
<WORD coords="1247,2595,1419,2519,2593">has</WORD>
<WORD coords="1489,2599,1729,2539,2597">come</WORD>
<WORD coords="1791,2601,1901,2531,2600">to</WORD>
<WORD coords="1957,2603,2073,2551,2601">mo</WORD>
<WORD coords="2143,2607,2259,2555,2607">as</WORD>
<WORD coords="2325,2611,2379,2559,2611">a</WORD>
<WORD coords="2443,2621,2801,2547,2617">result</WORD>
<WORD coords="2869,2621,2975,2551,2621">of</WORD>
</LINE>
<LINE>
<WORD coords="641,2681,817,2611,2681">the</WORD>
<WORD coords="887,2707,1121,2611,2685">trip</WORD>
<WORD coords="1189,2691,1301,2615,2691">is</WORD>
<WORD coords="1365,2695,1537,2623,2695">the</WORD>
<WORD coords="1605,2709,2265,2623,2702">association</WORD>
<WORD coords="2327,2715,2561,2641,2713">that</WORD>
<WORD coords="2633,2719,2683,2643,2719">I</WORD>
<WORD coords="2749,2723,2915,2647,2721">had</WORD>
</LINE>
<LINE>
<WORD coords="633,2787,879,2709,2784">with</WORD>
<WORD coords="943,2803,1123,2733,2791">you</WORD>
<WORD coords="1177,2793,1419,2721,2792">whom</WORD>
<WORD coords="1487,2797,1531,2723,2800">1</WORD>
<WORD coords="1601,2803,2017,2727,2801">admired</WORD>
<WORD coords="2083,2809,2433,2733,2807">before</WORD>
<WORD coords="2505,2817,2677,2743,2815">the</WORD>
<WORD coords="2751,2835,2975,2745,2819">trip</WORD>
</LINE>
<LINE>
<WORD coords="641,2885,753,2831,2885">as</WORD>
<WORD coords="823,2889,939,2833,2889">an</WORD>
<WORD coords="1005,2915,1461,2827,2892">earnest,</WORD>
<WORD coords="1543,2907,2071,2827,2902">efficient</WORD>
<WORD coords="2141,2911,2313,2843,2911">and</WORD>
<WORD coords="2381,2929,3031,2839,2919">high-minded</WORD>
</LINE>
<LINE>
<WORD coords="641,2993,1123,2915,2989">official</WORD>
<WORD coords="1187,2997,1351,2929,2997">and</WORD>
<WORD coords="1413,3001,1589,2927,2999">who</WORD>
<WORD coords="1659,3027,1877,2945,3003">now,</WORD>
<WORD coords="1959,3011,2249,2939,3009">after</WORD>
<WORD coords="2317,3033,2663,2941,3015">having</WORD>
<WORD coords="2747,3023,2913,2951,3022">ob-</WORD>
</LINE>
<LINE>
<WORD coords="645,3091,993,3021,3088">served</WORD>
<WORD coords="1061,3111,1237,3041,3097">you</WORD>
<WORD coords="1301,3099,1407,3027,3098">at</WORD>
<WORD coords="1481,3103,1769,3027,3100">close</WORD>
<WORD coords="1833,3131,2175,3051,3107">range,</WORD>
<WORD coords="2259,3113,2307,3041,3113">I</WORD>
<WORD coords="2377,3119,2613,3045,3117">have</WORD>
<WORD coords="2683,3129,3087,3051,3124">loarned</WORD>
</LINE>
<LINE>
<WORD coords="651,3187,749,3131,3186">t/O</WORD>
<WORD coords="819,3193,1047,3117,3191">love</WORD>
<WORD coords="1121,3195,1291,3125,3195">and</WORD>
<WORD coords="1355,3219,1767,3135,3201">respect</WORD>
<WORD coords="1841,3207,1951,3153,3206">as</WORD>
<WORD coords="2019,3209,2073,3155,3209">a</WORD>
<WORD coords="2141,3229,2677,3141,3215">gentleman</WORD>
<WORD coords="2739,3227,2911,3155,3225">and</WORD>
<WORD coords="2979,3229,3031,3175,3229">a</WORD>
</LINE>
<LINE>
<WORD coords="637,3295,1037,3215,3288">friend.</WORD>
</LINE>
</PARAGRAPH>
<PARAGRAPH>
<LINE>
<WORD coords="995,3523,1467,3423,3499">Thanking</WORD>
<WORD coords="1535,3523,1709,3451,3506">you</WORD>
<WORD coords="1775,3521,2073,3437,3512">again</WORD>
<WORD coords="2135,3519,2311,3445,3517">for</WORD>
<WORD coords="2379,3519,2551,3447,3518">the</WORD>
<WORD coords="2611,3541,3135,3451,3529">privilege</WORD>
</LINE>
<LINE>
<WORD coords="629,3607,809,3535,3591">you</WORD>
<WORD coords="869,3597,1103,3521,3595">have</WORD>
<WORD coords="1175,3607,1643,3533,3601">accorded</WORD>
<WORD coords="1703,3631,1871,3553,3608">me,</WORD>
<WORD coords="1959,3611,2001,3541,3611">I</WORD>
<WORD coords="2071,3617,2191,3557,3616">am</WORD>
</LINE>
</PARAGRAPH>
<PARAGRAPH>
<LINE>
<WORD coords="1585,3809,1879,3733,3806">Yours</WORD>
<WORD coords="1947,3831,2187,3755,3812">very</WORD>
<WORD coords="2249,3843,2587,3747,3818">truly,</WORD>
</LINE>
</PARAGRAPH>
</REGION>
</PAGECOLUMN>
<PAGECOLUMN>
<REGION backgroundColor="13481608">
<PARAGRAPH>
<LINE>
<WORD coords="1949,4219,2047,4143,4215">B.</WORD>
<WORD coords="2127,4221,2227,4143,4219">J.</WORD>
<WORD coords="2303,4227,2705,4147,4221">VALDiSS.</WORD>
</LINE>
</PARAGRAPH>
</REGION>
</PAGECOLUMN>
<PAGECOLUMN>
<REGION backgroundColor="13085043">
<PARAGRAPH>
<LINE>
<WORD coords="218,5694,270,5574,5694">8</WORD>
</LINE>
</PARAGRAPH>
</REGION>
</PAGECOLUMN>
<PAGECOLUMN>
<REGION backgroundColor="13480838">
<PARAGRAPH></PARAGRAPH>
</REGION>
</PAGECOLUMN>
<PAGECOLUMN>
<REGION backgroundColor="13085566">
<PARAGRAPH>
<LINE>
<WORD coords="4593,6120,4687,6011,6120">4</WORD>
</LINE>
</PARAGRAPH>
</REGION>
</PAGECOLUMN>
</HIDDENTEXT>
</OBJECT>
<MAP name="BVC-0398-062634-CP_0000.djvu"/>
</BODY>
</DjVuXML>
