<?xml version="1.0" encoding="UTF-8"?>
<!DOCTYPE DjVuXML>
<DjVuXML>
<BODY>
<OBJECT data="file://localhost//tmp/derive/memo-valdes-communication-service-between-manila-and-points-in-liberated-areas//BVC-0586-050945-BVL.djvu" height="7853" type="image/x.djvu" usemap="BVC-0586-050945-BVL_0000.djvu" width="4950">
<PARAM name="PAGE" value="BVC-0586-050945-BVL_0000.djvu"/>
<PARAM name="DPI" value="600"/>
<HIDDENTEXT>
<PAGECOLUMN></PAGECOLUMN>
<PAGECOLUMN>
<REGION backgroundColor="15978152">
<PARAGRAPH>
<LINE>
<WORD coords="591,1357,1203,1279,1351">Ei.ijUKiiiiiCxI</WORD>
<WORD coords="1261,1347,1429,1273,1345">for-</WORD>
<WORD coords="2051,1345,2133,1261,1345">/</WORD>
</LINE>
</PARAGRAPH>
<PARAGRAPH>
<LINE>
<WORD coords="581,1465,805,1395,1463">Hon.</WORD>
<WORD coords="889,1463,1303,1389,1460">Basilio</WORD>
<WORD coords="1381,1461,1475,1389,1461">J.</WORD>
<WORD coords="1549,1461,1909,1385,1457">Yal&lt;3ez</WORD>
<WORD coords="1979,1433,2053,1353,1433">^</WORD>
<WORD coords="3423,1425,3441,1403,1425">&apos;</WORD>
</LINE>
</PARAGRAPH>
<PARAGRAPH>
<LINE>
<WORD coords="583,1579,1127,1495,1563">Secretary</WORD>
<WORD coords="1199,1561,1307,1491,1561">of</WORD>
<WORD coords="1375,1563,1735,1487,1560">Health</WORD>
<WORD coords="1795,1559,1855,1493,1559">&amp;</WORD>
<WORD coords="1917,1555,2255,1477,1550">Public</WORD>
<WORD coords="2323,1547,2747,1475,1544">’&quot;elfare</WORD>
</LINE>
</PARAGRAPH>
<PARAGRAPH>
<LINE>
<WORD coords="899,1759,1371,1683,1756">SUU-Xi.cT;</WORD>
<WORD coords="1515,1757,2275,1671,1746">Conidurdcation</WORD>
<WORD coords="2343,1737,2753,1663,1733">service</WORD>
<WORD coords="2827,1749,2929,1661,1731">by</WORD>
<WORD coords="3005,1745,3577,1651,1727">Telegraph,</WORD>
<WORD coords="3665,1733,3997,1643,1715">Radio,</WORD>
<WORD coords="4115,1709,4307,1637,1708">&apos;.ir-</WORD>
</LINE>
<LINE>
<WORD coords="1631,1869,1919,1781,1849">plane</WORD>
<WORD coords="1989,1849,2389,1769,1841">Courier</WORD>
<WORD coords="2465,1835,2635,1781,1835">unu</WORD>
<WORD coords="2701,1837,3111,1759,1831">Vehicle</WORD>
<WORD coords="3185,1839,3641,1757,1823">CouT&apos;ier,</WORD>
<WORD coords="3725,1821,4135,1751,1816">between</WORD>
</LINE>
<LINE>
<WORD coords="1631,1953,1981,1879,1950">llanila</WORD>
<WORD coords="2051,1945,2211,1875,1943">and</WORD>
<WORD coords="2277,1941,2703,1867,1938">certain</WORD>
<WORD coords="2767,1953,3121,1863,1933">points</WORD>
<WORD coords="3189,1931,3299,1861,1930">in</WORD>
<WORD coords="3369,1933,3899,1853,1924">liberated</WORD>
<WORD coords="3967,1919,4299,1861,1916">areas.</WORD>
</LINE>
</PARAGRAPH>
<PARAGRAPH>
<LINE>
<WORD coords="907,2165,1147,2091,2165">lith</WORD>
<WORD coords="1215,2163,1629,2091,2160">further</WORD>
<WORD coords="1695,2153,2213,2085,2150">reference</WORD>
<WORD coords="2287,2145,2395,2075,2144">to</WORD>
<WORD coords="2467,2143,2635,2085,2141">our</WORD>
<WORD coords="2711,2137,3241,2063,2135">ineKioranda</WORD>
<WORD coords="3373,2131,3481,2061,2130">of</WORD>
<WORD coords="3551,2143,3845,2053,2127">ipril</WORD>
<WORD coords="3907,2141,4183,2045,2120">26th,</WORD>
</LINE>
<LINE>
<WORD coords="607,2283,783,2203,2269">i,:ay</WORD>
<WORD coords="849,2267,1027,2195,2267">5rd</WORD>
<WORD coords="1095,2267,1253,2197,2265">and</WORD>
<WORD coords="1335,2279,1553,2189,2264">4:th,</WORD>
<WORD coords="1639,2275,1909,2185,2263">1945,</WORD>
<WORD coords="1995,2261,2459,2179,2248">covering</WORD>
<WORD coords="2535,2243,2695,2171,2242">the</WORD>
<WORD coords="2775,2241,3325,2163,2237">estoblichi</WORD>
<WORD coords="3373,2233,3537,2163,2232">ent</WORD>
<WORD coords="3615,2229,3779,2157,2228">and</WORD>
<WORD coords="3853,2241,4413,2149,2220">operation;</WORD>
</LINE>
<LINE>
<WORD coords="611,2375,719,2307,2375">of</WORD>
<WORD coords="793,2375,963,2301,2371">the</WORD>
<WORD coords="1031,2375,1329,2297,2368">ebove</WORD>
<WORD coords="1401,2367,2163,2287,2359">comunication</WORD>
<WORD coords="2221,2351,2819,2273,2346">fccilitiee</WORD>
<WORD coords="2895,2341,3301,2267,2338">between</WORD>
<WORD coords="3375,2339,3729,2261,2333">^anila</WORD>
<WORD coords="3791,2327,3957,2269,2325">anc</WORD>
<WORD coords="4035,2325,4449,2253,2320">certc.^ii</WORD>
</LINE>
<LINE>
<WORD coords="613,2479,1153,2399,2473">liberated</WORD>
<WORD coords="1221,2483,1551,2413,2468">areas,</WORD>
<WORD coords="1627,2465,1747,2405,2463">v/e</WORD>
<WORD coords="1815,2459,1983,2403,2457">are</WORD>
<WORD coords="2049,2473,2457,2381,2452">pleased</WORD>
<WORD coords="2525,2447,2647,2379,2446">to</WORD>
<WORD coords="2715,2447,3123,2369,2443">furnish</WORD>
<WORD coords="3193,2457,3365,2385,2439">you</WORD>
<WORD coords="3437,2439,3601,2363,2435">the</WORD>
<WORD coords="3673,2445,4211,2359,2431">followins</WORD>
<WORD coords="4281,2423,4582,2365,2420">suituna^</WORD>
</LINE>
<LINE>
<WORD coords="607,2579,911,2503,2577">rized</WORD>
<WORD coords="979,2577,1213,2501,2575">list</WORD>
<WORD coords="1281,2571,1389,2501,2570">of</WORD>
<WORD coords="1467,2569,2227,2487,2562">coriiruunication</WORD>
<WORD coords="2287,2583,2889,2477,2552">facilities</WORD>
<WORD coords="2949,2543,3245,2469,2541">which</WORD>
<WORD coords="3323,2541,3479,2483,2539">ere</WORD>
<WORD coords="3559,2535,3725,2479,2533">now</WORD>
<WORD coords="3809,2533,4375,2459,2528">avtilable:</WORD>
</LINE>
</PARAGRAPH>
<PARAGRAPH>
<LINE>
<WORD coords="739,2783,833,2709,2782">1.</WORD>
<WORD coords="919,2783,1035,2715,2783">By</WORD>
<WORD coords="1101,2783,1627,2697,2772">Telegraph</WORD>
<WORD coords="1707,2769,2033,2695,2765">lines.</WORD>
<WORD coords="2173,2763,2825,2683,2753">T\7enty~four</WORD>
<WORD coords="2897,2763,3115,2663,2763">i{24)</WORD>
<WORD coords="3197,2743,3419,2671,2741">hour</WORD>
<WORD coords="3445,2757,3521,2689,2741">s_</WORD>
<WORD coords="3555,2757,3729,2673,2740">_^er</WORD>
<WORD coords="3709,2757,4017,2667,2737">_yi_^.</WORD>
</LINE>
</PARAGRAPH>
</REGION>
</PAGECOLUMN>
<PAGECOLUMN>
<REGION backgroundColor="16241324">
<PARAGRAPH>
<LINE>
<WORD coords="1223,2979,1335,2911,2977">To</WORD>
<WORD coords="1405,2991,1861,2899,2973">Llaloloa,</WORD>
<WORD coords="1945,2969,2355,2893,2964">Bulacan</WORD>
</LINE>
</PARAGRAPH>
<PARAGRAPH>
<LINE>
<WORD coords="1405,3077,1583,3011,3074">San</WORD>
<WORD coords="1647,3087,2157,2995,3068">Fernando,</WORD>
<WORD coords="2239,3077,2725,2991,3059">Pnmpenga</WORD>
</LINE>
<LINE>
<WORD coords="1407,3193,1807,3103,3176">Tarlac,</WORD>
<WORD coords="1895,3175,2055,3101,3171">Tar</WORD>
<WORD coords="2073,3167,2229,3097,3166">lac</WORD>
</LINE>
<LINE>
<WORD coords="1415,3295,1867,3203,3276">l^iqui&apos;,</WORD>
<WORD coords="1955,3273,2295,3197,3269">Tarlac</WORD>
</LINE>
<LINE>
<WORD coords="1407,3399,1871,3315,3379">Hagupan,</WORD>
<WORD coords="1951,3389,2539,3299,3371">Panousinen</WORD>
</LINE>
</PARAGRAPH>
</REGION>
</PAGECOLUMN>
<PAGECOLUMN>
<REGION backgroundColor="16306861">
<PARAGRAPH>
<LINE>
<WORD coords="743,3593,841,3521,3593">E.</WORD>
<WORD coords="929,3597,1043,3485,3597">^</WORD>
<WORD coords="1109,3595,1451,3515,3588">Radio.</WORD>
<WORD coords="1595,3583,1999,3513,3579">Twenty-</WORD>
<WORD coords="2017,3577,2237,3505,3574">four</WORD>
<WORD coords="2327,3577,2523,3483,3573">(E4)</WORD>
<WORD coords="2611,3567,2905,3491,3564">hours</WORD>
<WORD coords="2979,3559,3379,3487,3554">service</WORD>
<WORD coords="3403,3553,3425,3525,3553">.</WORD>
</LINE>
<LINE>
<WORD coords="1231,3793,1343,3725,3792">To</WORD>
<WORD coords="1411,3801,1931,3711,3785">Tacloban,</WORD>
<WORD coords="2011,3795,2305,3705,3777">Leyte</WORD>
<WORD coords="2819,3803,2831,3763,3803">,</WORD>
</LINE>
</PARAGRAPH>
</REGION>
</PAGECOLUMN>
<PAGECOLUMN>
<REGION backgroundColor="16504496">
<PARAGRAPH>
<LINE>
<WORD coords="743,4005,843,3925,4003">S,</WORD>
<WORD coords="925,4001,1213,3929,3998">t.lotor</WORD>
<WORD coords="1285,3995,1709,3919,3992">Vehicle</WORD>
<WORD coords="1777,3987,2181,3913,3983">Courier</WORD>
<WORD coords="2249,3981,2483,3919,3974">;&gt;erv</WORD>
<WORD coords="2499,3971,2717,3907,3971">ice.</WORD>
<WORD coords="2855,3971,3143,3899,3964">Leave</WORD>
<WORD coords="3213,3961,3575,3889,3959">i.iarxila</WORD>
</LINE>
</PARAGRAPH>
<PARAGRAPH>
<LINE>
<WORD coords="1227,4215,1577,4125,4200">Daily:</WORD>
<WORD coords="1715,4215,2053,4115,4190">Papig,</WORD>
<WORD coords="2135,4189,2427,4109,4184">Rizal</WORD>
</LINE>
</PARAGRAPH>
<PARAGRAPH>
<LINE>
<WORD coords="1719,4321,2111,4221,4297">Cavite,</WORD>
<WORD coords="2195,4289,2545,4211,4283">Cavite</WORD>
</LINE>
<LINE>
<WORD coords="1721,4405,2347,4321,4392">Oabenetuan,</WORD>
<WORD coords="2427,4385,2727,4315,4381">iiueva</WORD>
<WORD coords="2795,4391,3095,4305,4376">Lcija</WORD>
</LINE>
</PARAGRAPH>
<PARAGRAPH>
<LINE>
<WORD coords="1231,4623,1769,4533,4606">^.Iternate</WORD>
<WORD coords="1845,4617,2115,4527,4598">days:</WORD>
<WORD coords="2253,4605,2773,4519,4589">Satui-uay,</WORD>
<WORD coords="2859,4597,3249,4509,4578">i.onday,</WORD>
<WORD coords="3337,4585,3911,4495,4567">&apos;..ednesday,</WORD>
<WORD coords="3995,4577,4391,4489,4558">iricay,</WORD>
</LINE>
</PARAGRAPH>
<PARAGRAPH>
<LINE>
<WORD coords="1415,4711,1587,4635,4707">and</WORD>
<WORD coords="1661,4719,2053,4643,4703">LUJiuay.</WORD>
<WORD coords="2191,4697,2483,4627,4693">leave</WORD>
<WORD coords="2553,4691,2907,4593,4687">iTaaila</WORD>
<WORD coords="2983,4683,3207,4609,4680">7;00</WORD>
<WORD coords="3275,4679,3493,4603,4676">^t.M.</WORD>
</LINE>
</PARAGRAPH>
<PARAGRAPH>
<LINE>
<WORD coords="1477,4919,1591,4847,4918">To</WORD>
<WORD coords="1717,4925,2169,4819,4911">tialblos,</WORD>
<WORD coords="2253,4905,2675,4829,4900">Bulacan</WORD>
</LINE>
</PARAGRAPH>
<PARAGRAPH>
<LINE>
<WORD coords="1717,5019,1891,4951,5016">san</WORD>
<WORD coords="1951,5021,2467,4935,5008">Fernando,</WORD>
<WORD coords="2551,5025,3033,4933,4997">iampa/iga</WORD>
</LINE>
<LINE>
<WORD coords="1713,5135,2111,5043,5117">Tarlac,</WORD>
<WORD coords="2195,5113,2539,5037,5109">Tarlac</WORD>
</LINE>
<LINE>
<WORD coords="1717,5237,2169,5145,5219">Feniqui,</WORD>
<WORD coords="2249,5215,2601,5139,5211">Tailac</WORD>
</LINE>
<LINE>
<WORD coords="1713,5341,2169,5259,5331">laeufipnj</WORD>
<WORD coords="2251,5333,2859,5235,5310">Pangosirian</WORD>
</LINE>
<LINE>
<WORD coords="1713,5445,2227,5355,5427">Lingayen,</WORD>
<WORD coords="2307,5433,2915,5339,5413">i&apos;angosinen</WORD>
</LINE>
<LINE>
<WORD coords="1709,5535,1895,5469,5533">Sen</WORD>
<WORD coords="1947,5543,2463,5451,5527">Fernando,</WORD>
<WORD coords="2547,5525,2669,5451,5519">La</WORD>
<WORD coords="2729,5517,3035,5443,5513">Union</WORD>
</LINE>
</PARAGRAPH>
<PARAGRAPH>
<LINE>
<WORD coords="751,5759,847,5683,5756">4.</WORD>
<WORD coords="933,5755,1401,5677,5751">safehand</WORD>
<WORD coords="1467,5755,1943,5669,5743">Airplane</WORD>
<WORD coords="2015,5739,2467,5661,5734">Courier.</WORD>
<WORD coords="2663,5739,2955,5651,5725">‘ally*</WORD>
</LINE>
</PARAGRAPH>
</REGION>
</PAGECOLUMN>
<PAGECOLUMN>
<REGION backgroundColor="15385499">
<PARAGRAPH>
<LINE>
<WORD coords="1231,5957,1347,5887,5955">To</WORD>
<WORD coords="1413,5977,1649,5877,5958">Cfbu</WORD>
<WORD coords="1717,5965,1993,5871,5945">City,</WORD>
<WORD coords="2077,5945,2309,5869,5941">Cebu</WORD>
</LINE>
<LINE>
<WORD coords="1413,6065,1937,5973,6050">Tafiloban,</WORD>
<WORD coords="2021,6059,2307,5971,6041">Leyte</WORD>
</LINE>
<LINE>
<WORD coords="1419,6165,1949,6081,6149">Lingayen,</WORD>
<WORD coords="2031,6157,2625,6069,6138">Pangasinan</WORD>
</LINE>
</PARAGRAPH>
</REGION>
</PAGECOLUMN>
<PAGECOLUMN>
<REGION backgroundColor="14067833">
<PARAGRAPH>
<LINE>
<WORD coords="961,6323,1115,6253,6315">THC</WORD>
<WORD coords="1201,6315,1221,6267,6315">5</WORD>
<WORD coords="1691,6319,2033,6235,6308">weiilit</WORD>
<WORD coords="2099,6305,2627,6235,6299">-c-llowcmoe</WORD>
<WORD coords="2705,6295,2873,6227,6292">for</WORD>
<WORD coords="2943,6299,3413,6231,6285">luoDsagfes</WORD>
<WORD coords="3479,6285,3659,6217,6281">und</WORD>
<WORD coords="3713,6333,4135,6205,6272">precis</WORD>
<WORD coords="4205,6269,4325,6215,6268">on</WORD>
</LINE>
</PARAGRAPH>
<PARAGRAPH>
<LINE>
<WORD coords="981,6409,1199,6347,6407">thie</WORD>
<WORD coords="1825,6397,1983,6333,6393">uot</WORD>
<WORD coords="2059,6391,2169,6331,6388">to</WORD>
<WORD coords="2201,6403,2223,6387,6385">,</WORD>
<WORD coords="2233,6387,2585,6319,6385">exceed</WORD>
<WORD coords="2651,6424,3243,6303,6381">fiye^sjp</WORD>
</LINE>
</PARAGRAPH>
</REGION>
</PAGECOLUMN>
<PAGECOLUMN>
<REGION backgroundColor="15841927">
<PARAGRAPH>
<LINE>
<WORD coords="1011,6573,1101,6521,6564">in</WORD>
<WORD coords="1177,6573,1323,6499,6573">thi</WORD>
<WORD coords="1345,6573,1387,6527,6557">L-</WORD>
<WORD coords="1473,6573,1739,6507,6567">cohiif</WORD>
<WORD coords="1775,6567,2103,6487,6561">ctloii.</WORD>
<WORD coords="2183,6557,2477,6477,6553">allow</WORD>
<WORD coords="2547,6551,2661,6485,6548">us</WORD>
<WORD coords="2737,6543,2847,6471,6542">to</WORD>
<WORD coords="2915,6539,3199,6463,6535">ihvit</WORD>
<WORD coords="3327,6545,3355,6529,6545">„</WORD>
<WORD coords="4209,6537,4219,6529,6537">.</WORD>
</LINE>
</PARAGRAPH>
<PARAGRAPH>
<LINE>
<WORD coords="911,6687,1107,6633,6685">:?se-</WORD>
<WORD coords="1157,6693,1267,6619,6692">of</WORD>
<WORD coords="1339,6679,1631,6611,6677">t:»ea£</WORD>
<WORD coords="1699,6675,2287,6591,6669">facilities</WORD>
<WORD coords="2361,6661,2467,6583,6661">is</WORD>
<WORD coords="2543,6659,3141,6573,6652">restricted</WORD>
<WORD coords="3217,6643,3317,6567,6642">to</WORD>
<WORD coords="3349,6627,3355,6613,6627">■</WORD>
</LINE>
</PARAGRAPH>
<PARAGRAPH>
<LINE>
<WORD coords="689,6797,699,6787,6802">,</WORD>
<WORD coords="783,6807,899,6731,6802">rt</WORD>
<WORD coords="971,6801,1309,6723,6795">ovrici</WORD>
<WORD coords="1395,6791,1511,6717,6786">iff</WORD>
<WORD coords="1573,6813,1741,6695,6789">oi^</WORD>
<WORD coords="1817,6781,1929,6709,6781">to</WORD>
<WORD coords="1997,6777,2465,6693,6773">official</WORD>
<WORD coords="2535,6765,3013,6689,6760">business</WORD>
<WORD coords="3083,6769,3349,6679,6751">only,</WORD>
<WORD coords="4223,6729,4401,6665,6729">...^t</WORD>
</LINE>
</PARAGRAPH>
<PARAGRAPH>
<LINE>
<WORD coords="771,6913,893,6833,6911">It</WORD>
<WORD coords="969,6907,999,6855,6908">f</WORD>
<WORD coords="1029,6909,1065,6851,6911">V</WORD>
<WORD coords="1143,6911,1185,6839,6909">i</WORD>
<WORD coords="1209,6907,1249,6835,6907">l</WORD>
<WORD coords="1753,6897,1923,6819,6894">the</WORD>
<WORD coords="1985,6907,2381,6809,6888">public.</WORD>
</LINE>
</PARAGRAPH>
<PARAGRAPH>
<LINE>
<WORD coords="2013,7081,2177,6955,7081">^</WORD>
<WORD coords="2229,7055,2535,6979,7052">shall</WORD>
<WORD coords="2599,7051,2701,6975,7048">be</WORD>
<WORD coords="2767,7069,3309,6947,7037">o^ositou</WORD>
<WORD coords="3379,7035,3541,6961,7031">for</WORD>
<WORD coords="3621,7035,4091,6941,7018">dispateb</WORD>
</LINE>
</PARAGRAPH>
<PARAGRAPH>
<LINE>
<WORD coords="3273,7159,3297,7063,7159">(</WORD>
<WORD coords="3377,7131,3395,7109,7131">v</WORD>
<WORD coords="3443,7141,3677,7067,7138">tson</WORD>
<WORD coords="3743,7145,4315,7045,7126">Suiidif^ij).</WORD>
</LINE>
</PARAGRAPH>
</REGION>
</PAGECOLUMN>
<PAGECOLUMN>
<REGION backgroundColor="12815191">
<PARAGRAPH></PARAGRAPH>
</REGION>
</PAGECOLUMN>
<PAGECOLUMN>
<REGION backgroundColor="16038536">
<PARAGRAPH></PARAGRAPH>
</REGION>
</PAGECOLUMN>
<PAGECOLUMN></PAGECOLUMN>
<PAGECOLUMN>
<REGION backgroundColor="14920568">
<PARAGRAPH></PARAGRAPH>
</REGION>
</PAGECOLUMN>
<PAGECOLUMN>
<REGION backgroundColor="15380090">
<PARAGRAPH></PARAGRAPH>
</REGION>
</PAGECOLUMN>
</HIDDENTEXT>
</OBJECT>
<MAP name="BVC-0586-050945-BVL_0000.djvu"/>
</BODY>
</DjVuXML>
