<?xml version="1.0" encoding="UTF-8"?>
<files>
  <file name="BVC-0435-062738-CP.djvu" source="derivative">
    <format>DjVu</format>
    <original>BVC-0435-062738-CP_djvu.xml</original>
    <mtime>1452322234</mtime>
    <size>163233</size>
    <md5>5782c0bd14e2e1cc3a0229270c0e8b2d</md5>
    <crc32>de342907</crc32>
    <sha1>85941293aa1a2f37e6d3c6af02182bd4d97cac9e</sha1>
  </file>
  <file name="BVC-0435-062738-CP.gif" source="derivative">
    <format>Animated GIF</format>
    <original>BVC-0435-062738-CP_jp2.zip</original>
    <mtime>1451874720</mtime>
    <size>30278</size>
    <md5>673bbab5d5f009c2b2954ca5dce2979c</md5>
    <crc32>f4a70420</crc32>
    <sha1>02f16c9277d6bae965c10435d125f35c91c1befd</sha1>
  </file>
  <file name="BVC-0435-062738-CP.pdf" source="original">
    <mtime>1451874660</mtime>
    <size>817720</size>
    <md5>bf20f2b274e723a32ad7db4ad11c860c</md5>
    <crc32>36558783</crc32>
    <sha1>12a8b3a1456a65689efadb64cd3c54e5baaf8ec6</sha1>
    <format>Image Container PDF</format>
  </file>
  <file name="BVC-0435-062738-CP_abbyy.gz" source="derivative">
    <format>Abbyy GZ</format>
    <original>BVC-0435-062738-CP_jp2.zip</original>
    <mtime>1451874736</mtime>
    <size>23153</size>
    <md5>14b9439033c2e0c6d6101e2e6d7ea180</md5>
    <crc32>8d48495f</crc32>
    <sha1>dc02d267cd6633ac1dd2edf123bccde149c0d43a</sha1>
  </file>
  <file name="BVC-0435-062738-CP_djvu.txt" source="derivative">
    <format>DjVuTXT</format>
    <original>BVC-0435-062738-CP.djvu</original>
    <mtime>1452322240</mtime>
    <size>1327</size>
    <md5>c6d318727fd8d590006cc0369e789824</md5>
    <crc32>35c98175</crc32>
    <sha1>6790ceb5de28b85c819104d7cf9e5e87e6342ec8</sha1>
  </file>
  <file name="BVC-0435-062738-CP_djvu.xml" source="derivative">
    <format>Djvu XML</format>
    <original>BVC-0435-062738-CP_abbyy.gz</original>
    <mtime>1451874743</mtime>
    <size>13731</size>
    <md5>837b510bfc9e136fbf6f3853d14fbf08</md5>
    <crc32>8eaa1eb0</crc32>
    <sha1>f5bb2278ebbbee9a4b48c1ad772d3cad754b7dba</sha1>
  </file>
  <file name="BVC-0435-062738-CP_jp2.zip" source="derivative">
    <format>Single Page Processed JP2 ZIP</format>
    <original>BVC-0435-062738-CP.pdf</original>
    <mtime>1451874712</mtime>
    <size>1150594</size>
    <md5>7df1d29e7301f30a24713cc3f0d98e54</md5>
    <crc32>34907672</crc32>
    <sha1>097ef9c1a0540913c43f4782d9846669a46a1746</sha1>
  </file>
  <file name="BVC-0435-062738-CP_scandata.xml" source="derivative">
    <format>Scandata</format>
    <original>BVC-0435-062738-CP_djvu.xml</original>
    <mtime>1451874755</mtime>
    <size>895</size>
    <md5>19520508511a9764487c345db5b20e2a</md5>
    <crc32>04dd6278</crc32>
    <sha1>1a2ff8d80ba2a26b34078174bdbc5a709f04cb8b</sha1>
  </file>
  <file name="BVC-0435-062738-CP_text.pdf" source="derivative">
    <format>Additional Text PDF</format>
    <original>BVC-0435-062738-CP_djvu.xml</original>
    <mtime>1451874772</mtime>
    <size>252352</size>
    <md5>723f303357312f75e9a7e16e6b8db65a</md5>
    <crc32>6a2c1773</crc32>
    <sha1>02f8c99e61dcccc6456ce41f42a88b23298c8f68</sha1>
  </file>
  <file name="letter-basilio-valdes-from-manuel-azalte-appointment-as-constabulary-chief-june-27-1938_archive.torrent" source="metadata">
    <btih>4dec5f285b5a5f338859a342eff0fb1e5f41239a</btih>
    <mtime>1483258320</mtime>
    <size>3855</size>
    <md5>36664725e04ae22da49f46457d418fb7</md5>
    <crc32>b275a9a3</crc32>
    <sha1>4d4c31cb1b4a66fdce2a853e3c4e5dfb62068e5d</sha1>
    <format>Archive BitTorrent</format>
  </file>
  <file name="letter-basilio-valdes-from-manuel-azalte-appointment-as-constabulary-chief-june-27-1938_files.xml" source="original">
    <format>Metadata</format>
    <md5>ae5b0288884ecb23f98a9868f6826922</md5>
  </file>
  <file name="letter-basilio-valdes-from-manuel-azalte-appointment-as-constabulary-chief-june-27-1938_meta.sqlite" source="original">
    <mtime>1466407446</mtime>
    <size>9216</size>
    <format>Metadata</format>
    <md5>74b566bb65111f5052c33d62ba87ca0d</md5>
    <crc32>a1cb4aea</crc32>
    <sha1>58b67e4255526e4b5cdf57b6186e11e42ef7eb62</sha1>
  </file>
  <file name="letter-basilio-valdes-from-manuel-azalte-appointment-as-constabulary-chief-june-27-1938_meta.xml" source="original">
    <mtime>1483258319</mtime>
    <size>1442</size>
    <format>Metadata</format>
    <md5>04cea1234f18f0e537502c1307f9762e</md5>
    <crc32>caa8b703</crc32>
    <sha1>271ac7f44d11f0d80d9236c1ad773e417628e2ae</sha1>
  </file>
</files>
