<?xml version="1.0" encoding="UTF-8"?>
<metadata>
  <identifier>UnitedNationsReliefAndRehabilitationAdministration</identifier>
  <mediatype>texts</mediatype>
  <date>1943</date>
  <description>Reports of the Commitees of the Council&lt;br /&gt;First Session</description>
  <language>eng</language>
  <licenseurl>http://creativecommons.org/licenses/by-nd/3.0/</licenseurl>
  <scanner>Internet Archive HTML5 Uploader 1.6.1</scanner>
  <subject>Manuel L. Quezon</subject>
  <title>United Nations Relief And Rehabilitation Administration</title>
  <subject>United Nations</subject>
  <subject>Reports</subject>
  <publicdate>2015-05-14 15:08:55</publicdate>
  <uploader>cheng.bigay@pcdspo.gov.ph</uploader>
  <addeddate>2015-05-14 15:08:55</addeddate>
  <curation>[curator]validator@archive.org[/curator][date]20150514150937[/date][comment]checked for malware[/comment]</curation>
  <identifier-access>http://archive.org/details/UnitedNationsReliefAndRehabilitationAdministration</identifier-access>
  <identifier-ark>ark:/13960/t2v445f59</identifier-ark>
  <ppi>600</ppi>
  <ocr>ABBYY FineReader 9.0</ocr>
  <repub_state>4</repub_state>
  <collection>presidentmanuelquezon</collection>
  <collection>presidentialmuseumandlibrary</collection>
  <collection>additional_collections</collection>
  <backup_location>ia905305_22</backup_location>
</metadata>
