<?xml version="1.0" encoding="UTF-8"?>
<metadata>
  <identifier>letter-valdes-to-governor-kangelon-regarding-eo-23-november-7-1944</identifier>
  <mediatype>texts</mediatype>
  <date>1944-11-07</date>
  <description>Letter from Major General Basilio Valdes to Provincial Governor Kangleon (Tacloban, Leyte) regarding Executive Order No. 23, which created a Board of Inquiry to investigate charges of disloyalty to the Commonwealth of the Philippines and the United States of America in the province of Leyte</description>
  <language>eng</language>
  <scanner>Internet Archive HTML5 Uploader 1.6.3</scanner>
  <subject>Basilio Valdes; World War II; Leyte; official papers; Military; letters</subject>
  <title>Letter from Major General Basilio Valdes to Provincial Governor Kangleon (Tacloban, Leyte) regarding Executive Order No. 23</title>
  <publicdate>2015-12-08 08:35:05</publicdate>
  <uploader>cheng.bigay@pcdspo.gov.ph</uploader>
  <addeddate>2015-12-08 08:35:05</addeddate>
  <identifier-access>http://archive.org/details/letter-valdes-to-governor-kangelon-regarding-eo-23-november-7-1944</identifier-access>
  <identifier-ark>ark:/13960/t7gr0rs02</identifier-ark>
  <ppi>600</ppi>
  <ocr>ABBYY FineReader 11.0</ocr>
  <repub_state>4</repub_state>
  <collection>basiliovaldescollection</collection>
  <collection>presidentialmuseumandlibrary</collection>
  <collection>additional_collections</collection>
  <year>1944</year>
  <backup_location>ia905506_13</backup_location>
</metadata>
